Workbook

Sheet Depreciation (Non vehicle) Dec
B1: Chabé Luxury Transport LLC | J1: 46053
B3: Depreciation for the period -2026 | I3: As per Balance Sheet
B5: Sl. No. | C5: Particulars | D5: Cost of Asset | I5: Accumulated Depreciation | M5: Net Assets as on 31.12.2026
D6: Purchase date | E6: Opening | F6: Additions during year 2026 | G6: Sale /Disposal during year 2026 | H6: Asset Balance on 31.12.2026 | I6: Depreciation as on 01.01.2026 | J6: Dep Addition during year 2026 | K6: Dep deletion during year 2026 | L6: Net Depreciation as on 31.01.2026
C8: LEASEHOLD PROPERTY
B9: 1 | C9: Lease Hold Improvements | D9: 45261 | E9: 344855 | H9: =+E9+F9-G9 -> 344855 | I9: ='[1]Depreciation (Non vehicle) Dec'!$L$9 -> 239482.33 | J9: =((H9/3)*1/12) -> 9579.3056 | K9: 0 | L9: =+I9+J9-K9 -> 249061.64 | M9: =H9-L9 -> 95793.361
B10: 2 | C10: Lease Hold Improvements 2 | D10: 45373 | E10: 20000 | H10: =+E10-G10 -> 20000 | I10: ='[1]Depreciation (Non vehicle) Dec'!$L$10 -> 11666.667 | J10: =((H10/3)*1/12) -> 555.55556 | K10: 0 | L10: =+I10+J10-K10 -> 12222.222 | M10: =H10-L10 -> 7777.7778
B11: 3 | C11: Najmat Al Abeer | D11: 45426 | E11: 7500 | H11: =+E11-G11 -> 7500 | I11: ='[1]Depreciation (Non vehicle) Dec'!$L$11 -> 3958.3333 | J11: =((H11/3)*1/12) -> 208.33333 | K11: 0 | L11: =+I11+J11-K11 -> 4166.6667 | M11: =H11-L11 -> 3333.3333
B12: 4 | C12: DEWA approval | D12: 45581 | E12: 5891 | H12: =+E12-G12 -> 5891 | I12: ='[1]Depreciation (Non vehicle) Dec'!$L$12 -> 2290.9444 | J12: =((H12/3)*1/12) -> 163.63889 | K12: 0 | L12: =+I12+J12-K12 -> 2454.5833 | M12: =H12-L12 -> 3436.4167
B13: 5 | C13: Najm Al Almas | D13: 45646 | E13: 7500 | H13: =+E13-G13 -> 7500 | I13: ='[1]Depreciation (Non vehicle) Dec'!$L$13 -> 2500 | J13: =((H13/3)*1/12) -> 208.33333 | K13: 0 | L13: =+I13+J13-K13 -> 2708.3333 | M13: =H13-L13 -> 4791.6667
B14: 6 | C14: Najm Al Almas Building Constructing | D14: 45699 | E14: 3407 | H14: =+E14-G14 -> 3407 | I14: ='[1]Depreciation (Non vehicle) Dec'!$L$14 -> 946.38889 | J14: =((H14/3)*1/12) -> 94.638889 | L14: =+I14+J14-K14 -> 1041.0278 | M14: =H14-L14 -> 2365.9722
C15: Accumulated Depreciation Leasehold property | D15: TOTAL | E15: =SUM(E9:E14) -> 389153 | F15: =SUM(F9:F14) -> 0 | G15: =SUM(G9:G14) -> 0 | H15: =SUM(H9:H14) -> 389153 | I15: =SUM(I9:I14) -> 260844.67 | J15: =SUM(J9:J14) -> 10809.806 | K15: =SUM(K9:K14) -> 0 | L15: =SUM(L9:L14) -> 271654.47 | M15: =SUM(M9:M14) -> 117498.53
C17: ROU
B18: 1 | C18: Right of Use Asset | D18: 45292 | E18: 752267.99 | H18: =+E18+F18-G18 -> 752267.99 | I18: ='[1]Depreciation (Non vehicle) Dec'!$L$18 -> 543304.66 | J18: =(H18/3)*1/12 -> 20896.333 | L18: =+I18+J18-K18 -> 564201 | M18: =H18-L18 -> 188066.99
C20: Accumulated Depreciation on ROU | D20: TOTAL | E20: =SUM(E18:E19) -> 752267.99 | F20: =SUM(F18:F19) -> 0 | G20: =SUM(G18:G19) -> 0 | H20: =SUM(H18:H19) -> 752267.99 | I20: =SUM(I18:I19) -> 543304.66 | J20: =SUM(J18:J19) -> 20896.333 | K20: =SUM(K18:K19) -> 0 | L20: =SUM(L18:L19) -> 564201 | M20: =SUM(M18:M19) -> 188066.99
C22: FURNITURE & FIXTURES (TLT)
B23: 1 | C23: Furniture-Safe (Accounts + PRO Office) | D23: 44269 | E23: 2474.29 | G23: 0 | H23: =+E23+F23-G23 -> 2474.29 | I23: ='[1]Depreciation (Non vehicle) Dec'!$L$23 -> 2376.716 | J23: =((E23*20%)/12)*1 -> 41.238167 | K23: 0 | L23: =+I23+J23-K23 -> 2417.9542 | M23: =H23-L23 -> 56.335833
E24: =SUM(E22:E23) -> 2474.29 | F24: =SUM(F22:F23) -> 0 | G24: =SUM(G22:G23) -> 0 | H24: =SUM(H22:H23) -> 2474.29 | I24: =SUM(I22:I23) -> 2376.716 | J24: =SUM(J22:J23) -> 41.238167 | K24: =SUM(K22:K23) -> 0 | L24: =SUM(L22:L23) -> 2417.9542 | M24: =SUM(M22:M23) -> 56.335833
C25: FURNITURE & FIXTURES (Chabé)
B26: 2 | C26: Office chair | D26: 45159 | E26: 1890 | G26: 0 | H26: =+E26+F26-G26 -> 1890 | I26: ='[1]Depreciation (Non vehicle) Dec'!$L$26 -> 882 | J26: =((E26*20%)/12)*1 -> 31.5 | K26: 0 | L26: =+I26+J26-K26 -> 913.5 | M26: =H26-L26 -> 976.5
B27: 3 | C27: Office furniture -face to face work station Gray performance ergonomic chair Full white side cabinet L shape Meeting table Idesk Executive desk L shape manager desk Medium height cabinet Leather sofa Modern visitor chair | D27: 45252 | E27: 60961 | H27: =+E27+F27-G27 -> 60961 | I27: ='[1]Depreciation (Non vehicle) Dec'!$L$27 -> 25400.4 | J27: =((E27*20%)/12)*1 -> 1016.0167 | K27: 0 | L27: =+I27+J27-K27 -> 26416.417 | M27: =H27-L27 -> 34544.583
B28: 4 | C28: Office furniture-Bar table Bar stool Table top grey | D28: 45255 | E28: 2780 | H28: =+E28+F28-G28 -> 2780 | I28: ='[1]Depreciation (Non vehicle) Dec'!$L$28 -> 1158 | J28: =((E28*20%)/12)*1 -> 46.333333 | K28: 0 | L28: =+I28+J28-K28 -> 1204.3333 | M28: =H28-L28 -> 1575.6667
B29: 5 | C29: Office Furniture-Full height dark grey and white cabinet. Full height medium cabinet | D29: 45296 | E29: 7878.1 | H29: =+E29+F29-G29 -> 7878.1 | I29: ='[1]Depreciation (Non vehicle) Dec'!$L$29 -> 3019.9383 | J29: =((E29*20%)/12)*1 -> 131.30167 | L29: =+I29+J29-K29 -> 3151.24 | M29: =H29-L29 -> 4726.86
B30: 6 | C30: Kids car seat | D30: 45301 | E30: 2900 | H30: =+E30+F30-G30 -> 2900 | I30: ='[1]Depreciation (Non vehicle) Dec'!$L$30 -> 1111.6667 | J30: =((E30*20%)/12)*1 -> 48.333333 | L30: =+I30+J30-K30 -> 1160 | M30: =H30-L30 -> 1740
B31: 7 | C31: Dark Grey Sofa(Drivers room) | D31: 45351 | E31: 1990 | H31: 1900 | I31: ='[1]Depreciation (Non vehicle) Dec'!$L$31 -> 729.66667 | J31: =((E31*20%)/12)*1 -> 33.166667 | L31: =+I31+J31-K31 -> 762.83333 | M31: =H31-L31 -> 1137.1667
B32: 8 | C32: Cabinet/Mossjon Anthracite | D32: 45351 | E32: 710 | H32: =+E32+F32-G32 -> 710 | I32: ='[1]Depreciation (Non vehicle) Dec'!$L$32 -> 260.33333 | J32: =((E32*20%)/12)*1 -> 11.833333 | L32: =+I32+J32-K32 -> 272.16667 | M32: =H32-L32 -> 437.83333
B33: 9 | C33: Baby seat | D33: 45328 | E33: 714 | H33: =+E33+F33-G33 -> 714 | I33: ='[1]Depreciation (Non vehicle) Dec'!$L$33 -> 261.8 | J33: =((E33*20%)/12)*1 -> 11.9 | L33: =+I33+J33-K33 -> 273.7 | M33: =H33-L33 -> 440.3
E34: =SUM(E26:E33) -> 79823.1 | F34: =SUM(F26:F33) -> 0 | G34: =SUM(G26:G33) -> 0 | H34: =SUM(H26:H33) -> 79733.1 | I34: =SUM(I26:I33) -> 32823.805 | J34: =SUM(J26:J33) -> 1330.385 | K34: =SUM(K26:K33) -> 0 | L34: =SUM(L26:L33) -> 34154.19 | M34: =SUM(M26:M33) -> 45578.91
C36: Accumulated Depreciation-Furniture & Fixtures | D36: TOTAL | E36: =+E24+E34 -> 82297.39 | F36: =+F24+F34 -> 0 | G36: =+G24+G34 -> 0 | H36: =+H24+H34 -> 82207.39 | I36: =+I24+I34 -> 35200.521 | J36: =+J24+J34 -> 1371.6232 | K36: =+K24+K34 -> 0 | L36: =+L24+L34 -> 36572.144 | M36: =+M24+M34 -> 45635.246
C39: COMPUTER & EQUIPMENT (TLT)
C40: Office equipment
B41: 1 | C41: HP Laser printer MFP 135W (TLT_2211_001) | D41: 23/11/2022 | E41: 914 | H41: =+E41+F41-G41 -> 914 | I41: ='[1]Depreciation (Non vehicle) Dec'!$L$41 -> 563.46667 | J41: =((E41*20%)/12)*1 -> 15.233333 | K41: 0 | L41: =+I41+J41-K41 -> 578.7 | M41: =H41-L41 -> 335.3
B42: 2 | C42: Brother printer MFC-LC3750CDW (TLT_2102_001) | D42: 44245 | E42: 1297 | G42: 0 | H42: =+E42+F42-G42 -> 1297 | I42: ='[1]Depreciation (Non vehicle) Dec'!$L$42 -> 1262.7333 | J42: =((E42*20%)/12)*1 -> 21.616667 | K42: 0 | L42: =+I42+J42-K42 -> 1284.35 | M42: =H42-L42 -> 12.65
E43: =SUM(E41:E42) -> 2211 | F43: =SUM(F41:F42) -> 0 | G43: =SUM(G41:G42) -> 0 | H43: =SUM(H41:H42) -> 2211 | I43: =SUM(I41:I42) -> 1826.2 | J43: =SUM(J41:J42) -> 36.85 | K43: =SUM(K41:K42) -> 0 | L43: =SUM(L41:L42) -> 1863.05 | M43: =SUM(M41:M42) -> 347.95
C44: COMPUTER & IT EQUIPMENT (Chabé)
C45: Office equipment
B46: 1 | C46: Safe box (General Manager office) | D46: 45082 | E46: 2856 | H46: =+E46+F46-G46 -> 2856 | I46: ='[1]Depreciation (Non vehicle) Dec'!$L$50 -> 1475.6 | J46: =((E46*20%)/12)*1 -> 47.6 | L46: =+I46+J46-K46 -> 1523.2 | M46: =H46-L46 -> 1332.8
B47: 2 | C47: Microwave/Oven (Staff kitchen) | D47: 45255 | E47: 180 | H47: =+E47+F47-G47 -> 180 | I47: ='[1]Depreciation (Non vehicle) Dec'!$L$51 -> 75 | J47: =((E47*20%)/12)*1 -> 3 | L47: =+I47+J47-K47 -> 78 | M47: =H47-L47 -> 102
B48: 3 | C48: Fridge (Staff&Drivers kitchen) | D48: 45255 | E48: 950 | H48: =+E48+F48-G48 -> 950 | I48: ='[1]Depreciation (Non vehicle) Dec'!$L$52 -> 395.83333 | J48: =((E48*20%)/12)*1 -> 15.833333 | L48: =+I48+J48-K48 -> 411.66667 | M48: =H48-L48 -> 538.33333
B49: 4 | C49: Symphony Ind Air Cooler | D49: 45824 | E49: 3808.57 | H49: =+E49+F49-G49 -> 3808.57 | I49: ='[1]Depreciation (Non vehicle) Dec'!$L$53 -> 380.857 | J49: =((E49*20%)/12)*1 -> 63.476167 | L49: =+I49+J49-K49 -> 444.33317 | M49: =H49-L49 -> 3364.2368
C50: Television | M50: =H50-L50 -> 0
B51: 1 | C51: Samsung QA65Q70CA TV (DUSC_2401_001) | D51: 45316 | E51: 3046.67 | H51: =+E51-G51 -> 3046.67 | I51: ='[1]Depreciation (Non vehicle) Dec'!$L$55 -> 1218.668 | J51: =((E51*20%)/12)*1 -> 50.777833 | L51: =+I51+J51-K51 -> 1269.4458 | M51: =H51-L51 -> 1777.2242
E52: =SUM(E46:E51) -> 10841.24 | F52: =SUM(F46:F51) -> 0 | G52: =SUM(G46:G51) -> 0 | H52: =SUM(H46:H51) -> 10841.24 | I52: =SUM(I46:I51) -> 3545.9583 | J52: =SUM(J46:J51) -> 180.68733 | K52: =SUM(K46:K51) -> 0 | L52: =SUM(L46:L51) -> 3726.6457 | M52: =SUM(M46:M51) -> 7114.5943
C53: Cleaning Machine
B54: 1 | C54: Cleaning Scrubber drier machine (DUCLE_2312_001) | D54: 45266 | E54: 12000 | F54: 0 | H54: =+E54+F54-G54 -> 12000 | I54: ='[1]Depreciation (Non vehicle) Dec'!$L$58 -> 4800 | J54: =((E54*20%)/12)*1 -> 200 | L54: =+I54+J54-K54 -> 5000 | M54: =H54-L54 -> 7000
B55: 2 | C55: Garage -300 Injecter & Extracter (DUCLE_2401_001) | D55: 45301 | E55: 3400 | H55: =+E55+F55-G55 -> 3400 | I55: ='[1]Depreciation (Non vehicle) Dec'!$L$59 -> 1303.3333 | J55: =((E55*20%)/12)*1 -> 56.666667 | L55: =+I55+J55-K55 -> 1360 | M55: =H55-L55 -> 2040
B56: 3 | C56: Proliner 8.150Z TSS RLW (DUCLE_2401_002) | D56: 45301 | E56: 2700 | H56: =+E56+F56-G56 -> 2700 | I56: ='[1]Depreciation (Non vehicle) Dec'!$L$60 -> 1035 | J56: =((E56*20%)/12)*1 -> 45 | L56: =+I56+J56-K56 -> 1080 | M56: =H56-L56 -> 1620
B57: 4 | C57: Square Trolley (DUCLE_2401_003) | D57: 45302 | E57: 1600 | H57: =+E57+F57-G57 -> 1600 | I57: ='[1]Depreciation (Non vehicle) Dec'!$L$61 -> 613.33333 | J57: =((E57*20%)/12)*1 -> 26.666667 | L57: =+I57+J57-K57 -> 640 | M57: =H57-L57 -> 960
E58: =SUM(E54:E57) -> 19700 | F58: =SUM(F54:F57) -> 0 | G58: =SUM(G54:G57) -> 0 | H58: =SUM(H54:H57) -> 19700 | I58: =SUM(I54:I57) -> 7751.6667 | J58: =SUM(J54:J57) -> 328.33333 | K58: =SUM(K54:K57) -> 0 | L58: =SUM(L54:L57) -> 8080 | M58: =SUM(M54:M57) -> 11620
C60: Vehicle Charger
B61: 1 | C61: TERRA AC Charger 6AGC082157 (DUCLE_2312_002) | D61: 45268 | E61: 5395 | F61: 0 | H61: =+E61+F61-G61 -> 5395 | I61: ='[1]Depreciation (Non vehicle) Dec'!$L$65 -> 2158 | J61: =((E61*20%)/12)*1 -> 89.916667 | L61: =+I61+J61-K61 -> 2247.9167 | M61: =H61-L61 -> 3147.0833
E62: =SUM(E61) -> 5395 | F62: =SUM(F61) -> 0 | G62: =SUM(G61) -> 0 | H62: =SUM(H61) -> 5395 | I62: =SUM(I61) -> 2158 | J62: =SUM(J61) -> 89.916667 | K62: =SUM(K61) -> 0 | L62: =SUM(L61) -> 2247.9167 | M62: =SUM(M61) -> 3147.0833
C63: I PAD
B64: 1 | C64: PAD Pro 12.9 3RD 2018 (DUIP_2401_001) | D64: 45316 | E64: 1520 | H64: =+E64+F64-G64 -> 1520 | I64: ='[1]Depreciation (Non vehicle) Dec'!$L$68 -> 582.66667 | J64: =(E64*20%/12)*1 -> 25.333333 | L64: =+I64+J64-K64 -> 608 | M64: =H64-L64 -> 912
B65: 2 | C65: PAD Pro 12.9 3RD 2018 (DUIP_2401_002) | D65: 45316 | E65: 1520 | H65: =+E65+F65-G65 -> 1520 | I65: ='[1]Depreciation (Non vehicle) Dec'!$L$69 -> 582.66667 | J65: =(E65*20%/12)*1 -> 25.333333 | L65: =+I65+J65-K65 -> 608 | M65: =H65-L65 -> 912
B66: 3 | C66: PAD Pro 12.9 3RD 2018 (DUIP_2401_003) | D66: 45316 | E66: 1520 | H66: =+E66+F66-G66 -> 1520 | I66: ='[1]Depreciation (Non vehicle) Dec'!$L$70 -> 582.66667 | J66: =(E66*20%/12)*1 -> 25.333333 | L66: =+I66+J66-K66 -> 608 | M66: =H66-L66 -> 912
B67: 4 | C67: PAD Pro 12.9 3RD 2018 (DUIP_2401_004) | D67: 45316 | E67: 1520 | H67: =+E67+F67-G67 -> 1520 | I67: ='[1]Depreciation (Non vehicle) Dec'!$L$71 -> 582.66667 | J67: =(E67*20%/12)*1 -> 25.333333 | L67: =+I67+J67-K67 -> 608 | M67: =H67-L67 -> 912
B68: 5 | C68: PAD Pro 12.9 3RD 2018 (DUIP_2401_005) | D68: 45316 | E68: 1520 | H68: =+E68+F68-G68 -> 1520 | I68: ='[1]Depreciation (Non vehicle) Dec'!$L$72 -> 582.66667 | J68: =(E68*20%/12)*1 -> 25.333333 | L68: =+I68+J68-K68 -> 608 | M68: =H68-L68 -> 912
B69: 6 | C69: PAD Pro 12.9 3RD 2018 (DUIP_2401_006) | D69: 45316 | E69: 1520 | H69: =+E69+F69-G69 -> 1520 | I69: ='[1]Depreciation (Non vehicle) Dec'!$L$73 -> 582.66667 | J69: =(E69*20%/12)*1 -> 25.333333 | L69: =+I69+J69-K69 -> 608 | M69: =H69-L69 -> 912
B70: 7 | C70: Mac bbok Pro 16SB (Serial No:LDY0K74TGG) | D70: 45731 | E70: 10140.95 | H70: =+E70+F70-G70 -> 10140.95 | I70: ='[1]Depreciation (Non vehicle) Dec'!$L$74 -> 1521.1425 | J70: =(E70*20%/12)*1 -> 169.01583 | L70: =+I70+J70-K70 -> 1690.1583 | M70: =H70-L70 -> 8450.7917
B71: 8 | C71: I phone 16 Pro Max(Serial no:M02VH16HVV) | D71: 45731 | E71: 5064.76 | H71: =+E71+F71-G71 -> 5064.76 | I71: ='[1]Depreciation (Non vehicle) Dec'!$L$75 -> 759.714 | J71: =(E71*20%/12)*1 -> 84.412667 | L71: =+I71+J71-K71 -> 844.12667 | M71: =H71-L71 -> 4220.6333
B72: 9 | C72: IPAD Pro 12.9 3rd gem 256GB | D72: 45812 | E72: 6040 | H72: =+E72+F72-G72 -> 6040 | I72: ='[1]Depreciation (Non vehicle) Dec'!$L$76 -> 906 | J72: =(E72*20%/12)*1 -> 100.66667 | L72: =+I72+J72-K72 -> 1006.6667 | M72: =H72-L72 -> 5033.3333
B73: 10 | C73: Mac book Air | D73: 46004 | E73: 4760.95 | H73: =+E73+F73-G73 -> 4760.95 | I73: ='[1]Depreciation (Non vehicle) Dec'!$L$77 -> 714.1425 | J73: =(E73*20%/12)*1 -> 79.349167 | L73: =+I73+J73-K73 -> 793.49167 | M73: =H73-L73 -> 3967.4583
E74: =SUM(E64:E72) -> 30365.71 | F74: =SUM(F64:F72) -> 0 | G74: =SUM(G64:G72) -> 0 | H74: =SUM(H64:H73) -> 35126.66 | I74: =SUM(I64:I72) -> 6682.8565 | J74: =SUM(J64:J72) -> 506.09517 | K74: =SUM(K64:K72) -> 0 | L74: =SUM(L64:L72) -> 7188.9517 | M74: =SUM(M64:M72) -> 23176.758
C75: Laptop
B76: 1 | C76: HP PAV 15 EG2039NE (DUBLT_2309_001) | D76: 45197 | E76: 3904 | H76: =+E76+F76-G76 -> 3904 | I76: ='[1]Depreciation (Non vehicle) Dec'!$L$80 -> 1756.8 | J76: =((E76*20%)/12)*1 -> 65.066667 | L76: =+I76+J76-K76 -> 1821.8667 | M76: =H76-L76 -> 2082.1333
B77: 2 | C77: HP NB PA 13BE2011 (DUBLT_2309_002) | D77: 45197 | E77: 2761 | H77: =+E77+F77-G77 -> 2761 | I77: ='[1]Depreciation (Non vehicle) Dec'!$L$81 -> 1242.45 | J77: =((E77*20%)/12)*1 -> 46.016667 | L77: =+I77+J77-K77 -> 1288.4667 | M77: =H77-L77 -> 1472.5333
B78: 3 | C78: HP 15EG3014 (DUBLT_2310_001) | D78: 45215 | E78: 4380 | H78: =+E78+F78-G78 -> 4380 | I78: ='[1]Depreciation (Non vehicle) Dec'!$L$82 -> 1898 | J78: =((E78*20%)/12)*1 -> 73 | L78: =+I78+J78-K78 -> 1971 | M78: =H78-L78 -> 2409
B79: 4 | C79: HP 15EG3014_2 (DUBLT_2310_002) | D79: 45215 | E79: 4380 | H79: =+E79+F79-G79 -> 4380 | I79: ='[1]Depreciation (Non vehicle) Dec'!$L$83 -> 1898 | J79: =((E79*20%)/12)*1 -> 73 | L79: =+I79+J79-K79 -> 1971 | M79: =H79-L79 -> 2409
B80: 5 | C80: HP Elite book (DUBLT_2311_001) | D80: 45237 | E80: 4142.85 | H80: =+E80+F80-G80 -> 4142.85 | I80: ='[1]Depreciation (Non vehicle) Dec'!$L$84 -> 1726.1875 | J80: =((E80*20%)/12)*1 -> 69.0475 | L80: =+I80+J80-K80 -> 1795.235 | M80: =H80-L80 -> 2347.615
B81: 6 | C81: HP Elite book (DUBLT_2311_002) | D81: 45237 | E81: 4142.86 | H81: =+E81+F81-G81 -> 4142.86 | I81: ='[1]Depreciation (Non vehicle) Dec'!$L$85 -> 1726.1917 | J81: =((E81*20%)/12)*1 -> 69.047667 | L81: =+I81+J81-K81 -> 1795.2393 | M81: =H81-L81 -> 2347.6207
H82: =+E82+F82-G82 -> 0
E83: =SUM(E76:E82) -> 23710.71 | F83: =SUM(F76:F82) -> 0 | G83: =SUM(G76:G82) -> 0 | H83: =SUM(H76:H82) -> 23710.71 | I83: =SUM(I76:I82) -> 10247.629 | J83: =SUM(J76:J82) -> 395.1785 | K83: =SUM(K76:K82) -> 0 | L83: =SUM(L76:L82) -> 10642.808 | M83: =SUM(M76:M82) -> 13067.902
C84: Mobile Devices
B85: 1 | C85: Samsung A54 128LM (OPS phone) | D85: 45240 | E85: 1075 | F85: 0 | H85: =+E85+F85-G85 -> 1075 | I85: ='[1]Depreciation (Non vehicle) Dec'!$L$89 -> 475 | J85: =((E85*20%)/12)*1 -> 17.916667 | L85: =+I85+J85-K85 -> 492.91667 | M85: =H85-L85 -> 582.08333
B86: 2 | C86: Samsung A26 5G 128GB(FSJ cordinator) | D86: 45771 | E86: 904 | H86: =+E86+F86-G86 -> 904 | I86: ='[1]Depreciation (Non vehicle) Dec'!$L$90 -> 120.53333 | J86: =((E86*20%)/12)*1 -> 15.066667 | L86: =+I86+J86-K86 -> 135.6 | M86: =H86-L86 -> 768.4
B87: 3 | C87: Samsung A26 5G 128GB(MAA cordinator) | D87: 45772 | E87: 904 | H87: =+E87+F87-G87 -> 904 | I87: ='[1]Depreciation (Non vehicle) Dec'!$L$91 -> 120.53333 | J87: =((E87*20%)/12)*1 -> 15.066667 | L87: =+I87+J87-K87 -> 135.6 | M87: =H87-L87 -> 768.4
E89: =SUM(E85:E88) -> 2883 | F89: =SUM(F85:F88) -> 0 | G89: =SUM(G85:G88) -> 0 | H89: =SUM(H85:H88) -> 2883 | I89: =SUM(I85:I88) -> 716.06667 | J89: =SUM(J85:J88) -> 48.05 | K89: =SUM(K85:K88) -> 0 | L89: =SUM(L85:L88) -> 764.11667 | M89: =SUM(M85:M88) -> 2118.8833
C90: Printer
B91: 1 | C91: Brother printer MFC-LC3750CDW (DUBPT_2305_001) | D91: 45077 | E91: 1380 | H91: =+E91+F91-G91 -> 1380 | I91: ='[1]Depreciation (Non vehicle) Dec'!$L$95 -> 713 | J91: =((E91*20%)/12)*1 -> 23 | L91: =+I91+J91-K91 -> 736 | M91: =H91-L91 -> 644
B92: 2 | C92: HP MFP M479fdw (DUBPT_2306_001) | D92: 45085 | E92: 2298 | H92: =+E92+F92-G92 -> 2298 | I92: ='[1]Depreciation (Non vehicle) Dec'!$L$96 -> 1149.2 | J92: =((E92*20%)/12)*1 -> 38.3 | L92: =+I92+J92-K92 -> 1187.5 | M92: =H92-L92 -> 1110.5
B93: 3 | C93: HP Colour Laser Jet M 479fdw (DUBPT_2401_001) | D93: 45296 | E93: 2160 | H93: =+E93+F93-G93 -> 2160 | I93: ='[1]Depreciation (Non vehicle) Dec'!$L$97 -> 828 | J93: =((E93*20%)/12)*1 -> 36 | L93: =+I93+J93-K93 -> 864 | M93: =H93-L93 -> 1296
B94: 4 | C94: Ink tank GX6040 | D94: 45402 | E94: 2189.51 | H94: =+E94+F94-G94 -> 2189.51 | I94: ='[1]Depreciation (Non vehicle) Dec'!$L$98 -> 729.83667 | J94: =((E94*20%)/12)*1 -> 36.491833 | L94: =+I94+J94-K94 -> 766.3285 | M94: =H94-L94 -> 1423.1815
B95: 5 | C95: Canon Maxify GX6040 Ink printer | D95: 45726 | E95: 2657.36 | H95: =+E95+F95-G95 -> 2657.36 | I95: ='[1]Depreciation (Non vehicle) Dec'!$J$99 -> 398.604 | J95: =((E95*20%)/12)*1 -> 44.289333 | L95: =+I95+J95-K95 -> 442.89333 | M95: =H95-L95 -> 2214.4667
E96: =SUM(E91:E94) -> 8027.51 | F96: =SUM(F91:F94) -> 0 | G96: =SUM(G91:G94) -> 0 | H96: =SUM(H91:H95) -> 10684.87 | I96: =SUM(I91:I95) -> 3818.6407 | J96: =SUM(J91:J95) -> 178.08117 | K96: =SUM(K91:K95) -> 0 | L96: =SUM(L91:L95) -> 3996.7218 | M96: =SUM(M91:M95) -> 6688.1482
C97: Computer systems & Monitors
B98: 1 | C98: HP 290 G4 CORE 15 (DUBPC_2305_001) | D98: 45077 | E98: 1580 | H98: =+E98+F98-G98 -> 1580 | I98: ='[1]Depreciation (Non vehicle) Dec'!$L$102 -> 816.33333 | J98: =((E98*20%)/12)*1 -> 26.333333 | L98: =+I98+J98-K98 -> 842.66667 | M98: =H98-L98 -> 737.33333
B99: 2 | C99: HP 290 G4 CORE 17 (DUBPC_2305_002) | D99: 45077 | E99: 2050 | H99: =+E99+F99-G99 -> 2050 | I99: ='[1]Depreciation (Non vehicle) Dec'!$L$103 -> 1059.1667 | J99: =((E99*20%)/12)*1 -> 34.166667 | L99: =+I99+J99-K99 -> 1093.3333 | M99: =H99-L99 -> 956.66667
B100: 3 | C100: Ascus 90LM08U0B01170 Monitor 16 | D100: 45816 | E100: 1237.14 | H100: =+E100+F100-G100 -> 1237.14 | I100: ='[1]Depreciation (Non vehicle) Dec'!$L$104 -> 123.714 | J100: =((E100*20%)/12)*1 -> 20.619 | L100: =+I100+J100-K100 -> 144.333 | M100: =H100-L100 -> 1092.807
B101: 4 | C101: Ascus 90LM0890B01170 Monitor 15.6 | D101: 45816 | E101: 1190.48 | H101: =+E101+F101-G101 -> 1190.48 | I101: ='[1]Depreciation (Non vehicle) Dec'!$L$105 -> 119.048 | J101: =((E101*20%)/12)*1 -> 19.841333 | L101: =+I101+J101-K101 -> 138.88933 | M101: =H101-L101 -> 1051.5907
E102: =SUM(E98:E101) -> 6057.62 | F102: =SUM(F98:F101) -> 0 | G102: =SUM(G98:G101) -> 0 | H102: =SUM(H98:H101) -> 6057.62 | I102: =SUM(I98:I101) -> 2118.262 | J102: =SUM(J98:J101) -> 100.96033 | K102: =SUM(K98:K101) -> 0 | L102: =SUM(L98:L101) -> 2219.2223 | M102: =SUM(M98:M101) -> 3838.3977
C103: Screens
B104: 1 | C104: LG 38 Ultrawide curved LED (DUBSCR_2305_001) | D104: 45077 | E104: =2980*2 -> 5960 | H104: =+E104+F104-G104 -> 5960 | I104: ='[1]Depreciation (Non vehicle) Dec'!$L$108 -> 3079.3333 | J104: =((E104*20%)/12)*1 -> 99.333333 | L104: =+I104+J104-K104 -> 3178.6667 | M104: =H104-L104 -> 2781.3333
B105: 2 | C105: LG 38 Ultrawide curved LED (DUBSCR_2305_002)
B106: 3 | C106: LG 34 Ultrawide curved LED (DUBSCR_2305_003) | D106: 45077 | E106: 1380 | H106: =+E106+F106-G106 -> 1380 | I106: ='[1]Depreciation (Non vehicle) Dec'!$L$110 -> 713 | J106: =((E106*20%)/12)*1 -> 23 | L106: =+I106+J106-K106 -> 736 | M106: =H106-L106 -> 644
B107: 4 | C107: LG Monitor 24MP400 (DUBSCR_2305_004) | D107: 45077 | E107: 350 | H107: =+E107+F107-G107 -> 350 | I107: ='[1]Depreciation (Non vehicle) Dec'!$L$111 -> 180.83333 | J107: =((E107*20%)/12)*1 -> 5.8333333 | L107: =+I107+J107-K107 -> 186.66667 | M107: =H107-L107 -> 163.33333
B108: 5 | C108: Dell Vostro 2 desktop (DUBSCR_2308_001) | D108: 45159 | E108: 4020 | H108: =+E108+F108-G108 -> 4020 | I108: ='[1]Depreciation (Non vehicle) Dec'!$L$112 -> 1876 | J108: =((E108*20%)/12)*1 -> 67 | L108: =+I108+J108-K108 -> 1943 | M108: =H108-L108 -> 2077
B109: 6 | C109: Dell Vostro 2 desktop (DUBSCR_2308_002)
B110: 7 | C110: Samsung Curved Display (DUBSCR_2311_001) | D110: 45259 | E110: 1800 | H110: =+E110+F110-G110 -> 1800 | I110: ='[1]Depreciation (Non vehicle) Dec'!$L$114 -> 750 | J110: =((E110*20%)/12)*1 -> 30 | L110: =+I110+J110-K110 -> 780 | M110: =H110-L110 -> 1020
B111: 8 | C111: Samsung Curved Display (DUBSCR_2311_002)
...

Sheet Dep-Vehicle monthly Dec 2026
I1: Vehicle -Asset Balance
A2: No. | B2: Vehicle | C2: Plate No. | D2: Purchase Date | E2: Transfer /Sold Date | F2: Purchase price | G2: 30% total value | H2: 70% total value | I2: As on 01.01.2026 | J2: Addition 2026 | K2: Deletion 2026 | L2: As on 31.12.2026 | M2: DEPRECIATION | N2: Monthly | O2: Accumulated Depreciation 01.01.2026 | P2: 46023 | Q2: 46054 | R2: 46082 | S2: 46113 | T2: 46143 | U2: 46174 | V2: 46204 | W2: 46235 | X2: 46266 | Y2: 46296 | Z2: 46327 | AA2: 46357 | AB2: Total | AC2: Accumulated Depreciation Write off on sale | AD2: Accumulated Depreciation 31.12.2025 | AE2: Net Asset Balance as on 31.12.2025 | AF2: Over Depreciation for checking
AE3: =L3-AD3 -> 0
AE4: =L4-AD4 -> 0
B5: Own Cars | AE5: =L5-AD5 -> 0
A6: 1 | B6: Mercedes S-Class | C6: L 21982 | D6: 44769 | F6: 532380.95 | G6: =F6*30% -> 159714.28 | H6: =F6*70% -> 372666.66 | I6: 532380.95 | L6: =I6+J6-K6 -> 532380.95 | M6: =F6*30% -> 159714.28 | N6: =H6/36 -> 10351.852 | O6: 372666.74 | P6: 0 | AB6: =SUM(P6:AA6) -> 0 | AD6: =O6+AB6-AC6 -> 372666.74 | AE6: =L6-AD6 -> 159714.21 | AF6: =AE6-G6 -> -0.077638889
A7: 2 | B7: Mercedes EQS | C7: L 25144 | D7: 45061 | F7: 561102.33 | G7: =F7*30% -> 168330.7 | H7: =F7*70% -> 392771.63 | I7: 561102.33 | L7: =I7+J7-K7 -> 561102.33 | M7: =F7*30% -> 168330.7 | N7: =H7/36 -> 10910.323 | O7: 343028.82 | P7: =N7 -> 10910.323 | AB7: =SUM(P7:AA7) -> 10910.323 | AD7: =O7+AB7-AC7 -> 353939.14 | AE7: =L7-AD7 -> 207163.19 | AF7: =AE7-G7 -> 38832.491
A8: 3 | B8: Mercedes EQS 450 Plus | C8: L 25156 | D8: 45093 | F8: 561052.4 | G8: =F8*30% -> 168315.72 | H8: =F8*70% -> 392736.68 | I8: 561052.4 | L8: =I8+J8-K8 -> 561052.4 | M8: =F8*30% -> 168315.72 | N8: =H8/36 -> 10909.352 | O8: 331516.27 | P8: =N8 -> 10909.352 | AB8: =SUM(P8:AA8) -> 10909.352 | AD8: =O8+AB8-AC8 -> 342425.62 | AE8: =L8-AD8 -> 218626.78 | AF8: =AE8-G8 -> 50311.061
A9: 4 | B9: Mercedes 450M Saloon | C9: L 25161 | D9: 45093 | F9: 542957.2 | G9: =F9*30% -> 162887.16 | H9: =F9*70% -> 380070.04 | I9: 542957.2 | L9: =I9+J9-K9 -> 542957.2 | M9: =F9*30% -> 162887.16 | N9: =H9/36 -> 10557.501 | O9: 320824.07 | P9: =N9 -> 10557.501 | AB9: =SUM(P9:AA9) -> 10557.501 | AD9: =O9+AB9-AC9 -> 331381.57 | AE9: =L9-AD9 -> 211575.63 | AF9: =AE9-G9 -> 48688.466
A10: 5 | B10: Mercedes V-Class | C10: L 29681 | D10: 45168 | F10: 352380.95 | G10: =F10*30% -> 105714.29 | H10: =F10*70% -> 246666.66 | I10: 352380.95 | L10: =I10+J10-K10 -> 352380.95 | M10: =F10*30% -> 105714.29 | N10: =H10/36 -> 6851.8518 | O10: 191314.71 | P10: =N10 -> 6851.8518 | AB10: =SUM(P10:AA10) -> 6851.8518 | AD10: =O10+AB10-AC10 -> 198166.56 | AE10: =L10-AD10 -> 154214.39 | AF10: =AE10-G10 -> 48500.102
A11: 6 | B11: Maybach | C11: L 25417 | D11: 45183 | F11: 1300229.2 | G11: =F11*30% -> 390068.75 | H11: =F11*70% -> 910160.43 | I11: 1300229.2 | L11: =I11+J11-K11 -> 1300229.2 | M11: =F11*30% -> 390068.75 | N11: 28393 | O11: 668926.99 | P11: =N11 -> 28393 | AB11: =SUM(P11:AA11) -> 28393 | AD11: =O11+AB11-AC11 -> 697319.99 | AE11: =L11-AD11 -> 602909.19 | AF11: =AE11-G11 -> 212840.44
A12: 7 | B12: Mercedes V-Class | C12: L 25660 | D12: 45223 | F12: 449797 | G12: =F12*30% -> 134939.1 | H12: =F12*70% -> 314857.9 | I12: 449797 | L12: =I12+J12-K12 -> 449797 | M12: =F12*30% -> 134939.1 | N12: =H12/36 -> 8746.0528 | O12: 228384.19 | P12: =N12 -> 8746.0528 | AB12: =SUM(P12:AA12) -> 8746.0528 | AD12: =O12+AB12-AC12 -> 237130.25 | AE12: =L12-AD12 -> 212666.75 | AF12: =AE12-G12 -> 77727.654
A13: 8 | B13: Mercedes V-Class | C13: L 25310 | D13: 45225 | F13: 433333 | G13: =F13*30% -> 129999.9 | H13: =F13*70% -> 303333.1 | I13: 433333 | L13: =I13+J13-K13 -> 433333 | M13: =F13*30% -> 129999.9 | N13: =H13/36 -> 8425.9194 | O13: 219470.41 | P13: =N13 -> 8425.9194 | AB13: =SUM(P13:AA13) -> 8425.9194 | AD13: =O13+AB13-AC13 -> 227896.33 | AE13: =L13-AD13 -> 205436.67 | AF13: =AE13-G13 -> 75436.767
A14: 9 | B14: Mercedes V-Class | C14: L 24236 | D14: 45230 | F14: 428571 | G14: =F14*30% -> 128571.3 | H14: =F14*70% -> 299999.7 | I14: 428571 | L14: =I14+J14-K14 -> 428571 | M14: =F14*30% -> 128571.3 | N14: =H14/36 -> 8333.325 | O14: 215688.29 | P14: =N14 -> 8333.325 | AB14: =SUM(P14:AA14) -> 8333.325 | AD14: =O14+AB14-AC14 -> 224021.61 | AE14: =L14-AD14 -> 204549.39 | AF14: =AE14-G14 -> 75978.085
A15: 10 | B15: Mercedes S 500 | C15: L 29740 | D15: 45230 | F15: 627719 | G15: =F15*30% -> 188315.7 | H15: =F15*70% -> 439403.3 | I15: 627719 | L15: =I15+J15-K15 -> 627719 | M15: =F15*30% -> 188315.7 | N15: =H15/36 -> 12205.647 | O15: 315914.17 | P15: =N15 -> 12205.647 | AB15: =SUM(P15:AA15) -> 12205.647 | AD15: =O15+AB15-AC15 -> 328119.81 | AE15: =L15-AD15 -> 299599.19 | AF15: =AE15-G15 -> 111283.49
A16: 11 | B16: Mercedes S 500 | C16: L 25158 | D16: 45230 | F16: 627719 | G16: =F16*30% -> 188315.7 | H16: =F16*70% -> 439403.3 | I16: 627719 | L16: =I16+J16-K16 -> 627719 | M16: =F16*30% -> 188315.7 | N16: =H16/36 -> 12205.647 | O16: 315914.17 | P16: =N16 -> 12205.647 | AB16: =SUM(P16:AA16) -> 12205.647 | AD16: =O16+AB16-AC16 -> 328119.81 | AE16: =L16-AD16 -> 299599.19 | AF16: =AE16-G16 -> 111283.49
A17: 12 | B17: Mercedes Benz V class Avantgarde | C17: L 25173 | D17: 45240 | F17: 385714.29 | G17: =F17*30% -> 115714.29 | H17: =F17*70% -> 270000 | I17: 385714.29 | L17: =I17+J17-K17 -> 385714.29 | M17: =F17*30% -> 115714.29 | N17: =H17/36 -> 7500.0001 | O17: 191653.2 | P17: =N17 -> 7500.0001 | AB17: =SUM(P17:AA17) -> 7500.0001 | AD17: =O17+AB17-AC17 -> 199153.2 | AE17: =L17-AD17 -> 186561.09 | AF17: =AE17-G17 -> 70846.802
A18: 13 | B18: Mercedes Benz V class Avantgarde | C18: L 27891 | D18: 45260 | F18: 390476.19 | G18: =F18*30% -> 117142.86 | H18: =F18*70% -> 273333.33 | I18: 390476.19 | L18: =I18+J18-K18 -> 390476.19 | M18: =F18*30% -> 117142.86 | N18: =H18/36 -> 7592.5926 | O18: 189025.53 | P18: =N18 -> 7592.5926 | AB18: =SUM(P18:AA18) -> 7592.5926 | AD18: =O18+AB18-AC18 -> 196618.12 | AE18: =L18-AD18 -> 193858.07 | AF18: =AE18-G18 -> 76715.209
A19: 14 | B19: BMW I7 | C19: L 25784 | D19: 45268 | F19: 657142.86 | G19: =F19*30% -> 197142.86 | H19: =F19*70% -> 460000 | I19: 657142.86 | L19: =I19+J19-K19 -> 657142.86 | M19: =F19*30% -> 197142.86 | N19: =H19/36 -> 12777.778 | O19: 314754.55 | P19: =N19 -> 12777.778 | AB19: =SUM(P19:AA19) -> 12777.778 | AD19: =O19+AB19-AC19 -> 327532.33 | AE19: =L19-AD19 -> 329610.53 | AF19: =AE19-G19 -> 132467.67
A20: 15 | B20: Mercedes V-Class Extra long | C20: L 23498 | D20: 45350 | F20: 342857.14 | G20: =F20*30% -> 102857.14 | H20: =F20*70% -> 240000 | I20: 342857.14 | L20: =I20+J20-K20 -> 342857.14 | M20: =F20*30% -> 102857.14 | N20: =H20/36 -> 6666.6666 | O20: 146242.74 | P20: =N20 -> 6666.6666 | AB20: =SUM(P20:AA20) -> 6666.6666 | AD20: =O20+AB20-AC20 -> 152909.41 | AE20: =L20-AD20 -> 189947.73 | AF20: =AE20-G20 -> 87090.592
A21: 16 | B21: Mercedes V-Class Extra long | C21: L 25673 | D21: 45350 | F21: 342857.14 | G21: =F21*30% -> 102857.14 | H21: =F21*70% -> 240000 | I21: 342857.14 | L21: =I21+J21-K21 -> 342857.14 | M21: =F21*30% -> 102857.14 | N21: =H21/36 -> 6666.6666 | O21: 146242.74 | P21: =N21 -> 6666.6666 | AB21: =SUM(P21:AA21) -> 6666.6666 | AD21: =O21+AB21-AC21 -> 152909.41 | AE21: =L21-AD21 -> 189947.73 | AF21: =AE21-G21 -> 87090.592
A22: 17 | B22: BMW G70 735i | C22: L 26082 | D22: 45356 | F22: 448571.43 | G22: =F22*30% -> 134571.43 | H22: =F22*70% -> 314000 | I22: 448571 | L22: =I22+J22-K22 -> 448571 | M22: =F22*30% -> 134571.43 | N22: =H22/36 -> 8722.2222 | O22: 189613.33 | P22: =N22 -> 8722.2222 | AB22: =SUM(P22:AA22) -> 8722.2222 | AD22: =O22+AB22-AC22 -> 198335.55 | AE22: =L22-AD22 -> 250235.45 | AF22: =AE22-G22 -> 115664.02
A23: 18 | B23: BMW G70 735i | C23: L 26081 | D23: 45356 | F23: 448571.43 | G23: =F23*30% -> 134571.43 | H23: =F23*70% -> 314000 | I23: 448571 | L23: =I23+J23-K23 -> 448571 | M23: =F23*30% -> 134571.43 | N23: =H23/36 -> 8722.2222 | O23: 189613.33 | P23: =N23 -> 8722.2222 | AB23: =SUM(P23:AA23) -> 8722.2222 | AD23: =O23+AB23-AC23 -> 198335.55 | AE23: =L23-AD23 -> 250235.45 | AF23: =AE23-G23 -> 115664.02
... A27: 22 | B27: Mercedes S Class | C27: L 23717 | D27: 45687 | F27: 623809.52 | G27: =F27*30% -> 187142.86 | H27: =F27*70% -> 436666.66 | I27: 623809.52 | L27: =I27+J27-K27 -> 623809.52 | M27: =F27*30% -> 187142.86 | N27: =H27/36 -> 12129.63 | O27: 133425.93 | P27: =N27 -> 12129.63 | AB27: =SUM(P27:AA27) -> 12129.63 | AD27: =O27+AB27-AC27 -> 145555.55 | AE27: =L27-AD27 -> 478253.97 | AF27: =AE27-G27 -> 291111.11
A28: 23 | B28: Mercedes V Class | C28: L 69535 | D28: 45713 | F28: =475238.09+4886.38 -> 480124.47 | G28: =F28*30% -> 144037.34 | H28: =F28*70% -> 336087.13 | I28: =475238.09+4886.38 -> 480124.47 | L28: =I28+J28-K28 -> 480124.47 | M28: =F28*30% -> 144037.34 | N28: =H28/36 -> 9335.7536 | O28: 94359.534 | P28: =N28 -> 9335.7536 | AB28: =SUM(P28:AA28) -> 9335.7536 | AD28: =O28+AB28-AC28 -> 103695.29 | AE28: =L28-AD28 -> 376429.18 | AF28: =AE28-G28 -> 232391.84
A29: 24 | B29: Mercedes S Class | C29: L 72913 | D29: 45713 | F29: =570476.19+5865.62 -> 576341.81 | G29: =F29*30% -> 172902.54 | H29: =F29*70% -> 403439.27 | I29: =570476.19+5865.62 -> 576341.81 | L29: =I29+J29-K29 -> 576341.81 | M29: =F29*30% -> 172902.54 | N29: =H29/36 -> 11206.646 | O29: 113269.28 | P29: =N29 -> 11206.646 | AB29: =SUM(P29:AA29) -> 11206.646 | AD29: =O29+AB29-AC29 -> 124475.92 | AE29: =L29-AD29 -> 451865.89 | AF29: =AE29-G29 -> 278963.34
A30: 25 | B30: Escalade ESV | C30: L 44136 | D30: 45848 | F30: 541904.76 | G30: =F30*30% -> 162571.43 | H30: =F30*70% -> 379333.33 | I30: 541904.76 | L30: =I30+J30-K30 -> 541904.76 | M30: =F30*30% -> 162571.43 | N30: =H30/36 -> 10537.037 | O30: 59823.178 | P30: =N30 -> 10537.037 | AB30: =SUM(P30:AA30) -> 10537.037 | AD30: =O30+AB30-AC30 -> 70360.215 | AE30: =L30-AD30 -> 471544.55 | AF30: =AE30-G30 -> 308973.12
A31: 26 | B31: BMW Série 7 | C31: L 98573 | D31: 45930 | F31: =510000-24285.71 -> 485714.29 | G31: =F31*30% -> 145714.29 | H31: =F31*70% -> 340000 | I31: =510000-24285.71 -> 485714.29 | L31: =I31+J31-K31 -> 485714.29 | M31: =F31*30% -> 145714.29 | N31: =H31/36 -> 9444.4445 | O31: 28333.334 | P31: =N31 -> 9444.4445 | AB31: =SUM(P31:AA31) -> 9444.4445 | AD31: =+O31+AB31 -> 37777.778 | AE31: =L31-AD31 -> 447936.51 | AF31: =AE31-G31 -> 302222.22
A32: 27 | B32: Mercedes V-Class | C32: L 28406 | D32: 45947 | F32: 504761.9 | G32: =F32*30% -> 151428.57 | H32: =F32*70% -> 353333.33 | I32: 504761.9 | L32: =I32+J32-K32 -> 504761.9 | M32: =F32*30% -> 151428.57 | N32: =H32/36 -> 9814.8147 | O32: 23745.519 | P32: =N32 -> 9814.8147 | AB32: =SUM(P32:AA32) -> 9814.8147 | AD32: =O32+AB32-AC32 -> 33560.334 | AE32: =L32-AD32 -> 471201.57 | AF32: =AE32-G32 -> 319773
A33: 28 | B33: Mercedes S 450 | C33: L 92860 | D33: 45965 | F33: 537142.86 | G33: =F33*30% -> 161142.86 | H33: =F33*70% -> 376000 | I33: 537142.86 | L33: =I33+J33-K33 -> 537142.86 | M33: =F33*30% -> 161142.86 | N33: =H33/36 -> 10444.444 | O33: 19496.296 | P33: =N33 -> 10444.444 | AB33: =SUM(P33:AA33) -> 10444.444 | AD33: =O33+AB33-AC33 -> 29940.741 | AE33: =L33-AD33 -> 507202.12 | AF33: =AE33-G33 -> 346059.26
A34: 29 | B34: GMC Yokon | C34: L 94684 | D34: 45994 | F34: 352380.95 | G34: =F34*30% -> 105714.29 | H34: =F34*70% -> 246666.66 | I34: 352380.95 | L34: =I34+J34-K34 -> 352380.95 | M34: =F34*30% -> 105714.29 | N34: =H34/36 -> 6851.8518 | O34: 6188.7694 | P34: =N34 -> 6851.8518 | AB34: =SUM(P34:AA34) -> 6851.8518 | AD34: =O34+AB34-AC34 -> 13040.621 | AE34: =L34-AD34 -> 339340.33 | AF34: =AE34-G34 -> 233626.04
A35: 30 | B35: Mercedes V300 sty | C35: L 26509 | D35: 45996 | F35: 504761.9 | G35: =F35*30% -> 151428.57 | H35: =F35*70% -> 353333.33 | I35: 504761.9 | L35: =I35+J35-K35 -> 504761.9 | M35: =F35*30% -> 151428.57 | N35: =H35/36 -> 9814.8147 | O35: 8231.7801 | P35: =N35 -> 9814.8147 | AB35: =SUM(P35:AA35) -> 9814.8147 | AD35: =O35+AB35-AC35 -> 18046.595 | AE35: =L35-AD35 -> 486715.31 | AF35: =AE35-G35 -> 335286.74
F38: 480124.47 | G38: =F38*30% -> 144037.34 | H38: =F38*70% -> 336087.13 | M38: =G38 -> 144037.34 | N38: =H38/36 -> 9335.7536 | Q38: =N38-Q28 -> 9335.7536 | R38: =R35-R28 -> 0 | S38: =N38-S28 -> 9335.7536 | T38: =N38 -> 9335.7536
F39: 576341.81 | G39: =F39*30% -> 172902.54 | H39: =F39*70% -> 403439.27 | M39: =G39 -> 172902.54 | N39: =H39/36 -> 11206.646 | Q39: =N39-Q29 -> 11206.646 | R39: =R36-R29 -> 0 | S39: =N39-S29 -> 11206.646 | T39: =N39 -> 11206.646
AD40: =O40+AB40-AC40 -> 0 | AE40: =L40-AD40 -> 0
B41: Sold Vehicles | AE41: =L41-AD41 -> 0
AD44: =O44+AB44-AC44 -> 0
I45: =SUM(I6:I44) -> 15535612 | J45: =SUM(J6:J44) -> 0 | K45: =SUM(K6:K44) -> 0 | L45: =SUM(L6:L44) -> 15535612 | M45: =SUM(M6:M44) -> 4977623.8 | N45: =SUM(N6:N44) -> 325734.53 | O45: =SUM(O6:O44) -> 5735569.9 | P45: =SUM(P6:P44) -> 294840.28 | ... S45: =SUM(S6:S44) -> 20542.4 | T45: =SUM(T6:T32) -> 0 | U45: =SUM(U6:U44) -> 0 | V45: =SUM(V6:V44) -> 0 | W45: =SUM(W6:W44) -> 0 | X45: =SUM(X6:X44) -> 0 | Y45: =SUM(Y6:Y44) -> 0 | Z45: =SUM(Z6:Z44) -> 0 | AA45: =SUM(AA6:AA44) -> 0 | AB45: =SUM(AB6:AB44) -> 294840.28 | ... AE45: =SUM(AE6:AE44) -> 9505202
L50: 15826091
L51: =+L45-L50 -> -290479.25
AB52: Balance as per Zoho on 31.01.2026 | AD52: 5735569.8 | AE52: =+L50-AD52 -> 10090522
AD53: =+AD45-AD52 -> 294840.32 | AE53: =+AE45-AE52 -> -585319.57

Sheet Feuil2
K2: L 21982
K3: L 22197
K4: L 23498
K5: L 23717
K6: L 24236
K7: L 24644
K8: L 25144
K9: L 25156
K10: L 25158
K11: L 25161
K12: L 25173
K13: L 25310
... K31: L 98573

Sheet Feuil1
A1: 561102.33 | B1: =A1*20% -> 112220.47 | C1: =B1/12 -> 9351.7055
A2: 561052.4 | B2: =A2*20% -> 112210.48 | C2: =B2/12 -> 9350.8733
A3: 542957.2 | B3: =A3*20% -> 108591.44 | C3: =B3/12 -> 9049.2867
A4: 352380.95 | B4: =A4*20% -> 70476.19 | C4: =B4/12 -> 5873.0158
A5: 1300229.2 | B5: =A5*20% -> 260045.84 | C5: =B5/12 -> 21670.486
A6: 449797 | B6: =A6*20% -> 89959.4 | C6: =B6/12 -> 7496.6167
A7: 433333 | B7: =A7*20% -> 86666.6 | C7: =B7/12 -> 7222.2167
A8: 428571 | B8: =A8*20% -> 85714.2 | C8: =B8/12 -> 7142.85
A9: 627719 | B9: =A9*20% -> 125543.8 | C9: =B9/12 -> 10461.983
A10: 627719 | B10: =A10*20% -> 125543.8 | C10: =B10/12 -> 10461.983
A11: 385714.29 | B11: =A11*20% -> 77142.858 | C11: =B11/12 -> 6428.5715
A12: 390476.19 | B12: =A12*20% -> 78095.238 | C12: =B12/12 -> 6507.9365
... A21: 623809.52 | B21: =A21*20% -> 124761.9 | C21: =B21/12 -> 10396.825
A22: =475238.09+4886.38 -> 480124.47 | B22: =A22*20% -> 96024.894 | C22: =B22/12 -> 8002.0745
A23: =570476.19+5865.62 -> 576341.81 | B23: =A23*20% -> 115268.36 | C23: =B23/12 -> 9605.6968
A24: 541904.76 | B24: =A24*20% -> 108380.95 | C24: =B24/12 -> 9031.746
A25: =510000-24285.71 -> 485714.29 | B25: =A25*20% -> 97142.858 | C25: =B25/12 -> 8095.2382
A26: 504761.9 | B26: =A26*20% -> 100952.38 | C26: =B26/12 -> 8412.6983
C27: =SUM(C1:C26) -> 226815.77

Sheet Car List
B2: SALE LIST | J2: Car List as on Feb 28th 2025
B3: 2024 | J3: 1 | K3: Audi A6 | L3: L 29677
B4: Vehicle | C4: Plate No. | D4: Transfer/Sold Plate no: | E4: Purchase Date | F4: Transfer /Sold Date | J4: 1 | K4: Cadillac Escalade | L4: L 25789
B5: V-Class | C5: L 23416 | D5: SALE | E5: 43478 | F5: 17.05.2024 | J5: 2 | K5: Cadillac Escalade | L5: L 28857
B6: Tesla | C6: L 23717 | D6: SALE | E6: 43509 | F6: 14.05.2024 | J6: 3 | K6: Cadillac Escalade | L6: L 29673
B7: Cadillac | C7: L 23254 | D7: SALE | E7: 43453 | F7: 27.03.2024 | J7: 4 | K7: Chevrolet Suburban | L7: L 29741
B8: S-Class | C8: L 25341 | D8: SALE | E8: 43787 | F8: 08.01.2024 | J8: 5 | K8: Mercedes S Class 450 | L8: L 28794
B9: Honda Odyssey | C9: L 26081 | D9: SALE | E9: 44075 | F9: 05.03.2024 | J9: 6 | K9: Mercedes S-Class | L9: L 29875
B10: Honda Odyssey | C10: L 26082 | D10: SALE | E10: 44075 | F10: 31.01.2024 | J10: 7 | K10: Mercedes S-Class | L10: L 95118
B11: Lexus | C11: L 25673 | D11: New india/Total loss | E11: 44075 | F11: 16.01.2024 | J11: 8 | K11: Mercedes S-Class | L11: L 23269
B12: Mercedes S-Class | C12: L 22197 | D12: New india/Total loss | E12: 44561 | F12: 06.03.2024 | J12: 9 | K12: Mercedes S-Class | L12: L 21982
B13: Honda Odyssey | C13: L 26080 | D13: Transfer | E13: 44075 | F13: 13.03.2024 | J13: 10 | K13: Mercedes V-Class | L13: L 23872
B14: Tesla | C14: L 23752 | D14: SALE | E14: 43552 | F14: 27.06.2024 | J14: 11 | K14: Mercedes V-Class | L14: L 25149
B15: V-Class | C15: L 25235 | D15: SALE | E15: 43751 | F15: 08.10.2024 | J15: 12 | K15: Mercedes EQS | L15: L 25144
B16: BMW | C16: L 25321 | D16: SALE | E16: 43828 | F16: 07.10.2024 | J16: 13 | K16: Mercedes EQS 450 Plus | L16: L 25156
B17: Mercedes V-Class | C17: L 29361 | D17: New india/Total loss | E17: 44833 | F17: 45572 | J17: 14 | K17: Mercedes 450M Saloon | L17: L 25161
B18: BMW | C18: L 61233 | D18: SALE | E18: 44437 | F18: 45624 | J18: 15 | K18: Mercedes V-Class | L18: L 29681
B19: Honda Odyssey(F) | C19: L 24163 | D19: Transfer | E19: 44075 | F19: 28.06.2024 | J19: 16 | K19: Maybach | L19: L 25417
B20: Mercedes V-Class | C20: L 29678 | D20: SALE | E20: 44451 | F20: 45642 | J20: 17 | K20: Mercedes V-Class | L20: L 25660
B21: BMW | C21: L 38108 | D21: SALE | E21: 44437 | F21: 45636 | J21: 18 | K21: Mercedes V-Class | L21: L 25310
B22: Mercedes V-Class | C22: L 24644 | D22: SALE | E22: 44459 | F22: 45636 | J22: 19 | K22: Mercedes V-Class | L22: L 24236
B23: 2025 | J23: 20 | K23: Mercedes S 500 | L23: L 29740
B24: Vehicle | C24: Plate No. | D24: Transfer/Sold Plate no: | E24: Purchase Date | F24: Transfer /Sold Date | J24: 21 | K24: Mercedes S 500 | L24: L 25158
B25: Audi A6 | C25: L 29677 | D25: Sold | E25: 44478 | F25: 45757 | J25: 22 | K25: Mercedes Benz V class Avantgarde | L25: L 25173
J26: 23 | K26: Mercedes Benz V class Avantgarde | L26: L 27891
J27: 24 | K27: BMW I7 | L27: L 22082
J28: 25 | K28: BMW I7 | L28: L 25784
J29: 26 | K29: Mercedes V-Class Extra long | L29: L 23498
J30: 27 | K30: Mercedes V-Class Extra long | L30: L 25673
J31: 28 | K31: BMW G70 735i | L31: L 26082
J32: 29 | K32: BMW G70 735i | L32: L 26081
J33: 30 | K33: BMW G60 520. | L33: L 22197
J34: 31 | K34: Mercedes S Class | L34: L 24644
J35: 32 | K35: Mercedes S Class | L35: L26080
J36: 33 | K36: Mercedes S Class | L36: L 23717
J37: 34 | K37: Mercedees V Class
B38: Vehicle | C38: Plate No. | D38: Transfer/Sold Plate no: | E38: Transfer /Sold Date | J38: 35 | K38: Mercedes S Class
B39: S-Class | C39: L 25341 | D39: SALE | E39: 08.01.2024
B40: Lexus | C40: L 25673 | D40: New india/Total loss | E40: 16.01.2024
B41: Honda Odyssey | C41: L 26082 | D41: SALE | E41: 31.01.2024
B42: Honda Odyssey | C42: L 26081 | D42: SALE | E42: 05.03.2024
B43: Mercedes S-Class | C43: L 22197 | D43: New india/Total loss | E43: 06.03.2024
B44: Honda Odyssey | C44: L 26080 | D44: Transfer | E44: 13.03.2024
B45: Cadillac | C45: L 23254 | D45: SALE | E45: 27.03.2024

Sheet Simulation 2025_26_27_28
J1: Vehicle -Asset Balance
A2: No. | B2: Vehicle | C2: Plate No. | D2: Transfer/Sold Plate no: | E2: Purchase Date | F2: Transfer /Sold Date | G2: Purchase price | H2: 30% total value | I2: 70% total value | J2: As on 01.01.2024 | K2: Addition 2024 | L2: Deletion 2024 | M2: As on 31.12.2024 | N2: DEPRECIATION | O2: Monthly | P2: Accumulated Depreciaiton 01.01.2024 | Q2: Additional depreciation Adjustment amount | R2: Balance depreciation (3 years) | S2: Monthly revised dep | T2: 45292 | U2: 45323 | V2: 45352 | W2: 45383 | X2: 45413 | Y2: May-24' Adjusted Depreciation | Z2: 45444 | AA2: Jun-24' Adjusted Depreciation | AB2: 45474 | AC2: Jul-24' Adjusted Depreciation | AD2: 45505 | AE2: Aug-24' Adjusted Depreciation | AF2: 45536 | AG2: Sep-24' Adjusted Depreciation | AH2: 45566 | AI2: Oct-24' Adjusted Depreciation | AJ2: 45597 | AK2: Nov-24' Adjusted Depreciation | AL2: 45627 | AM2: Dec-24' Adjusted Depreciation | AN2: Total | AO2: Accumulated Depreciation Write off on sale | AP2: Accumulated Depreciation 31.12.2024 | AQ2: Net Asset Balance as on 31.12.2024 | AS2: 45658 | AT2: =EDATE(AS2,1) -> 45689 | AU2: =EDATE(AT2,1) -> 45717 | AV2: =EDATE(AU2,1) -> 45748 | AW2: =EDATE(AV2,1) -> 45778 | AX2: =EDATE(AW2,1) -> 45809 | AY2: =EDATE(AX2,1) -> 45839 | AZ2: =EDATE(AY2,1) -> 45870 | BA2: =EDATE(AZ2,1) -> 45901 | ... CN2: =EDATE(CM2,1) -> 47088
AQ3: =M3-AP3 -> 0
AQ4: =M4-AP4 -> 0
B5: Own Cars | AQ5: =M5-AP5 -> 0
A6: 1 | B6: Audi A6 | C6: L 29677 | E6: 44478 | G6: 170476.19 | H6: =G6*30% -> 51142.857 | I6: =G6*70% -> 119333.33 | J6: 170476.19 | M6: =J6+K6-L6 -> 170476.19 | N6: =G6*20% -> 34095.238 | O6: =N6/12 -> 2841.2698 | P6: 75889.405 | Q6: 17374.304 | R6: 17545.814 | S6: 3289.8402 | T6: =ROUND($O$6,2) -> 2841.27 | U6: =ROUND($O$6,2) -> 2841.27 | V6: =ROUND($O$6,2) -> 2841.27 | W6: =ROUND($O$6,2) -> 2841.27 | X6: 3289.8402 | Y6: 2724.9439 | Z6: =X6 -> 3289.8402 | AA6: =Y6 -> 2724.9439 | AB6: =Z6 -> 3289.8402 | AC6: =AA6 -> 2724.9439 | AD6: =AB6 -> 3289.8402 | AE6: =AC6 -> 2724.9439 | AF6: =AD6 -> 3289.8402 | AG6: 2724.94 | AH6: 3289.8402 | AI6: 908.31 | AJ6: -2193.23 | AK6: 0 | AL6: 0 | AM6: 0 | AN6: =SUM(T6:AM6) -> 43443.917 | AP6: =P6+AN6-AO6 -> 119333.32 | AQ6: =M6-AP6 -> 51142.869 | AS6: =IF(AQ6>H6,(AL6+AM6),0) -> 0 | AT6: =IF(AS6+IF(AS6="0","0",AS6)>AQ6,0,AS6) -> 0 | AU6: =IF(SUM($AS6:AT$6)+IF(AT6="0","0",AT6)>$AQ6,0,AT6) -> 0 | AV6: =IF(SUM($AS6:AU$6)+IF(AU6="0","0",AU6)>$AQ6,0,AU6) -> 0 | AW6: =IF(SUM($AS6:AV$6)+IF(AV6="0","0",AV6)>$AQ6,0,AV6) -> 0 | AX6: =IF(SUM($AS6:AW$6)+IF(AW6="0","0",AW6)>$AQ6,0,AW6) -> 0 | AY6: =IF(SUM($AS6:AX$6)+IF(AX6="0","0",AX6)>$AQ6,0,AX6) -> 0 | AZ6: =IF(SUM($AS6:AY$6)+IF(AY6="0","0",AY6)>$AQ6,0,AY6) -> 0 | BA6: =IF(SUM($AS6:AZ$6)+IF(AZ6="0","0",AZ6)>$AQ6,0,AZ6) -> 0 | BB6: =IF(SUM($AS6:BA$6)+IF(BA6="0","0",BA6)>$AQ6,0,BA6) -> 0 | ... CN6: =IF(SUM($AS6:CM$6)+IF(CM6="0","0",CM6)>$AQ6,0,CM6) -> 0
A7: 2 | B7: Cadillac Escalade | C7: L 25789 | E7: 44516 | G7: 366666.67 | H7: =G7*30% -> 110000 | I7: =G7*70% -> 256666.67 | J7: 366666.67 | M7: =J7+K7-L7 -> 366666.67 | N7: =G7*20% -> 73333.334 | O7: =N7/12 -> 6111.1112 | P7: 155629.6 | Q7: 36058.378 | R7: 46645.358 | S7: 7067.4785 | T7: =ROUND($O$7,2) -> 6111.11 | U7: =ROUND($O$7,2) -> 6111.11 | V7: =ROUND($O$7,2) -> 6111.11 | W7: =ROUND($O$7,2) -> 6111.11 | X7: 7067.4785 | Y7: 4537.4648 | Z7: =X7 -> 7067.4785 | AA7: =Y7 -> 4537.4648 | AB7: =Z7 -> 7067.4785 | AC7: =AA7 -> 4537.4648 | AD7: =AB7 -> 7067.4785 | AE7: =AC7 -> 4537.4648 | AF7: =AD7 -> 7067.4785 | AG7: 4537.46 | AH7: 7067.4785 | AI7: 4537.46 | AJ7: 4240.49 | AK7: 2722.48 | AL7: 0 | AM7: 0 | AN7: =SUM(T7:AM7) -> 101037.06 | AP7: =P7+AN7-AO7 -> 256666.66 | AQ7: =M7-AP7 -> 110000.01 | AS7: =IF(AQ7>H7,(AL7+AM7),0) -> 0 | AT7: =IF(AS7+IF(AS7="0","0",AS7)>AQ7,0,AS7) -> 0 | AU7: =IF(SUM($AS7:AT$7)+IF(AT7="0","0",AT7)>$AQ7,0,AT7) -> 0 | AV7: =IF(SUM($AS7:AU$7)+IF(AU7="0","0",AU7)>$AQ7,0,AU7) -> 0 | AW7: =IF(SUM($AS7:AV$7)+IF(AV7="0","0",AV7)>$AQ7,0,AV7) -> 0 | AX7: =IF(SUM($AS7:AW$7)+IF(AW7="0","0",AW7)>$AQ7,0,AW7) -> 0 | AY7: =IF(SUM($AS7:AX$7)+IF(AX7="0","0",AX7)>$AQ7,0,AX7) -> 0 | AZ7: =IF(SUM($AS7:AY$7)+IF(AY7="0","0",AY7)>$AQ7,0,AY7) -> 0 | BA7: =IF(SUM($AS7:AZ$7)+IF(AZ7="0","0",AZ7)>$AQ7,0,AZ7) -> 0 | BB7: =IF(SUM($AS7:BA$7)+IF(BA7="0","0",BA7)>$AQ7,0,BA7) -> 0 | ... CN7: =IF(SUM($AS7:CM$7)+IF(CM7="0","0",CM7)>$AQ7,0,CM7) -> 0
A8: 3 | B8: Cadillac Escalade | C8: L 28857 | E8: 44524 | G8: 420952.38 | H8: =G8*30% -> 126285.71 | I8: =G8*70% -> 294666.67 | J8: 420952.38 | M8: =J8+K8-L8 -> 420952.38 | N8: =G8*20% -> 84190.476 | O8: =N8/12 -> 7015.873 | P8: 178670.83 | Q8: 39244.119 | R8: 55704.109 | S8: 8112.249 | T8: =ROUND($O$8,2) -> 7015.87 | U8: =ROUND($O$8,2) -> 7015.87 | V8: =ROUND($O$8,2) -> 7015.87 | W8: =ROUND($O$8,2) -> 7015.87 | X8: 8112.249 | Y8: 4693.4344 | Z8: =X8 -> 8112.249 | AA8: =Y8 -> 4693.4344 | AB8: =Z8 -> 8112.249 | AC8: =AA8 -> 4693.4344 | AD8: =AB8 -> 8112.249 | AE8: =AC8 -> 4693.4344 | AF8: =AD8 -> 8112.249 | AG8: 4693.43 | AH8: 8112.249 | AI8: 4693.43 | AJ8: 7030.62 | AK8: 4067.64 | AL8: 0 | AM8: 0 | AN8: =SUM(T8:AM8) -> 115995.83 | AP8: =P8+AN8-AO8 -> 294666.66 | AQ8: =M8-AP8 -> 126285.72 | AS8: =IF(AQ8>H8,(AL8+AM8),0) -> 0 | AT8: =IF(AS8+IF(AS8="0","0",AS8)>AQ8,0,AS8) -> 0 | AU8: =IF(SUM($AS$8:AT8)+IF(AT8="0","0",AT8)>$AQ8,0,AT8) -> 0 | AV8: =IF(SUM($AS$8:AU8)+IF(AU8="0","0",AU8)>$AQ8,0,AU8) -> 0 | AW8: =IF(SUM($AS$8:AV8)+IF(AV8="0","0",AV8)>$AQ8,0,AV8) -> 0 | AX8: =IF(SUM($AS$8:AW8)+IF(AW8="0","0",AW8)>$AQ8,0,AW8) -> 0 | AY8: =IF(SUM($AS$8:AX8)+IF(AX8="0","0",AX8)>$AQ8,0,AX8) -> 0 | AZ8: =IF(SUM($AS$8:AY8)+IF(AY8="0","0",AY8)>$AQ8,0,AY8) -> 0 | BA8: =IF(SUM($AS$8:AZ8)+IF(AZ8="0","0",AZ8)>$AQ8,0,AZ8) -> 0 | BB8: =IF(SUM($AS$8:BA8)+IF(BA8="0","0",BA8)>$AQ8,0,BA8) -> 0 | ... CN8: =IF(SUM($AS$8:CM8)+IF(CM8="0","0",CM8)>$AQ8,0,CM8) -> 0
A9: 4 | B9: Cadillac Escalade | C9: L 29673 | E9: 44516 | G9: 420952.38 | H9: =G9*30% -> 126285.71 | I9: =G9*70% -> 294666.67 | J9: 420952.38 | M9: =J9+K9-L9 -> 420952.38 | N9: =G9*20% -> 84190.476 | O9: =N9/12 -> 7015.873 | P9: 176799.93 | Q9: 43267.835 | R9: 53551.294 | S9: 8113.8324 | T9: =ROUND($O$9,2) -> 7015.87 | U9: =ROUND($O$9,2) -> 7015.87 | V9: =ROUND($O$9,2) -> 7015.87 | W9: =ROUND($O$9,2) -> 7015.87 | X9: 8113.8324 | Y9: 5492.7219 | Z9: =X9 -> 8113.8324 | AA9: =Y9 -> 5492.7219 | AB9: =Z9 -> 8113.8324 | AC9: =AA9 -> 5492.7219 | AD9: =AB9 -> 8113.8324 | AE9: =AC9 -> 5492.7219 | AF9: =AD9 -> 8113.8324 | AG9: 5492.72 | AH9: 8113.8324 | AI9: 5492.72 | AJ9: 4868.3 | AK9: 3295.63 | AL9: 0 | AM9: 0 | AN9: =SUM(T9:AM9) -> 117866.73 | AP9: =P9+AN9-AO9 -> 294666.66 | AQ9: =M9-AP9 -> 126285.72 | AS9: =IF(AQ9>H9,(AL9+AM9),0) -> 0 | AT9: =IF(AS9+IF(AS9="0","0",AS9)>AQ9,0,AS9) -> 0 | AU9: =IF(SUM($AS$9:AT9)+IF(AT9="0","0",AT9)>$AQ9,0,AT9) -> 0 | AV9: =IF(SUM($AS$9:AU9)+IF(AU9="0","0",AU9)>$AQ9,0,AU9) -> 0 | AW9: =IF(SUM($AS$9:AV9)+IF(AV9="0","0",AV9)>$AQ9,0,AV9) -> 0 | AX9: =IF(SUM($AS$9:AW9)+IF(AW9="0","0",AW9)>$AQ9,0,AW9) -> 0 | AY9: =IF(SUM($AS$9:AX9)+IF(AX9="0","0",AX9)>$AQ9,0,AX9) -> 0 | AZ9: =IF(SUM($AS$9:AY9)+IF(AY9="0","0",AY9)>$AQ9,0,AY9) -> 0 | BA9: =IF(SUM($AS$9:AZ9)+IF(AZ9="0","0",AZ9)>$AQ9,0,AZ9) -> 0 | BB9: =IF(SUM($AS$9:BA9)+IF(BA9="0","0",BA9)>$AQ9,0,BA9) -> 0 | ... CN9: =IF(SUM($AS$9:CM9)+IF(CM9="0","0",CM9)>$AQ9,0,CM9) -> 0
A10: 5 | B10: Chevrolet Suburban | C10: L 29741 | E10: 44481 | G10: 196500 | H10: =G10*30% -> 58950 | I10: =G10*70% -> 137550 | J10: 196500 | M10: =J10+K10-L10 -> 196500 | N10: =G10*20% -> 39300 | O10: =N10/12 -> 3275 | P10: 87157.258 | Q10: 19966.646 | R10: 20601.096 | S10: 3791.6127 | T10: =ROUND($O$10,2) -> 3275 | U10: =ROUND($O$10,2) -> 3275 | V10: =ROUND($O$10,2) -> 3275 | W10: =ROUND($O$10,2) -> 3275 | X10: 3791.6127 | Y10: 3072.0821 | Z10: =X10 -> 3791.6127 | AA10: =Y10 -> 3072.0821 | AB10: =Z10 -> 3791.6127 | AC10: =AA10 -> 3072.0821 | AD10: =AB10 -> 3791.6127 | AE10: =AC10 -> 3072.0821 | AF10: =AD10 -> 3791.6127 | AG10: 3072.08 | AH10: 3791.6127 | AI10: 1331.24 | AJ10: -2148.58 | AK10: 0 | AL10: 0 | AM10: 0 | AN10: =SUM(T10:AM10) -> 50392.745 | AP10: =P10+AN10-AO10 -> 137550 | AQ10: =M10-AP10 -> 58949.997 | AS10: =IF(AQ10>H10,(AL10+AM10),0) -> 0 | AT10: =IF(AS10+IF(AS10="0","0",AS10)>AQ10,0,AS10) -> 0 | AU10: =IF(SUM($AS$10:AT10)+IF(AT10="0","0",AT10)>$AQ10,0,AT10) -> 0 | AV10: =IF(SUM($AS$10:AU10)+IF(AU10="0","0",AU10)>$AQ10,0,AU10) -> 0 | AW10: =IF(SUM($AS$10:AV10)+IF(AV10="0","0",AV10)>$AQ10,0,AV10) -> 0 | AX10: =IF(SUM($AS$10:AW10)+IF(AW10="0","0",AW10)>$AQ10,0,AW10) -> 0 | AY10: =IF(SUM($AS$10:AX10)+IF(AX10="0","0",AX10)>$AQ10,0,AX10) -> 0 | AZ10: =IF(SUM($AS$10:AY10)+IF(AY10="0","0",AY10)>$AQ10,0,AY10) -> 0 | BA10: =IF(SUM($AS$10:AZ10)+IF(AZ10="0","0",AZ10)>$AQ10,0,AZ10) -> 0 | BB10: =IF(SUM($AS$10:BA10)+IF(BA10="0","0",BA10)>$AQ10,0,BA10) -> 0 | ... CN10: =IF(SUM($AS$10:CM10)+IF(CM10="0","0",CM10)>$AQ10,0,CM10) -> 0
A11: 6 | B11: Mercedes S Class 450 | C11: L 28794 | E11: 44521 | G11: 523761.91 | H11: =G11*30% -> 157128.57 | I11: =G11*70% -> 366633.34 | J11: 523761.91 | M11: =J11+K11-L11 -> 523761.91 | N11: =G11*20% -> 104752.38 | O11: =N11/12 -> 8729.3652 | P11: 220853.05 | Q11: 51287.879 | R11: 68304.293 | S11: 10094.23 | T11: =ROUND($O$11,2) -> 8729.37 | U11: =ROUND($O$11,2) -> 8729.37 | V11: =ROUND($O$11,2) -> 8729.37 | W11: =ROUND($O$11,2) -> 8729.37 | X11: 10094.23 | Y11: 6289.4349 | Z11: =X11 -> 10094.23 | AA11: =Y11 -> 6289.4349 | AB11: =Z11 -> 10094.23 | AC11: =AA11 -> 6289.4349 | AD11: =AB11 -> 10094.23 | AE11: =AC11 -> 6289.4349 | AF11: =AD11 -> 10094.23 | AG11: 6289.43 | AH11: 10094.23 | AI11: 6289.43 | AJ11: 7738.91 | AK11: 4821.9 | AL11: 0 | AM11: 0 | AN11: =SUM(T11:AM11) -> 145780.27 | AP11: =P11+AN11-AO11 -> 366633.33 | AQ11: =M11-AP11 -> 157128.58 | AS11: =IF(AQ11>H11,(AL11+AM11),0) -> 0 | AT11: =IF(AS11+IF(AS11="0","0",AS11)>AQ11,0,AS11) -> 0 | AU11: =IF(SUM($AS$11:AT11)+IF(AT11="0","0",AT11)>$AQ11,0,AT11) -> 0 | AV11: =IF(SUM($AS$11:AU11)+IF(AU11="0","0",AU11)>$AQ11,0,AU11) -> 0 | AW11: =IF(SUM($AS$11:AV11)+IF(AV11="0","0",AV11)>$AQ11,0,AV11) -> 0 | AX11: =IF(SUM($AS$11:AW11)+IF(AW11="0","0",AW11)>$AQ11,0,AW11) -> 0 | AY11: =IF(SUM($AS$11:AX11)+IF(AX11="0","0",AX11)>$AQ11,0,AX11) -> 0 | AZ11: =IF(SUM($AS$11:AY11)+IF(AY11="0","0",AY11)>$AQ11,0,AY11) -> 0 | BA11: =IF(SUM($AS$11:AZ11)+IF(AZ11="0","0",AZ11)>$AQ11,0,AZ11) -> 0 | BB11: =IF(SUM($AS$11:BA11)+IF(BA11="0","0",BA11)>$AQ11,0,BA11) -> 0 | ... CN11: =IF(SUM($AS$11:CM11)+IF(CM11="0","0",CM11)>$AQ11,0,CM11) -> 0
A12: 7 | B12: Mercedes S-Class | C12: L 29875 | E12: 44672 | G12: 532380.95 | H12: =G12*30% -> 159714.28 | I12: =G12*70% -> 372666.66 | J12: 532380.95 | M12: =J12+K12-L12 -> 532380.95 | N12: =G12*20% -> 106476.19 | O12: =ROUND(N12/12,2) -> 8873.02 | P12: 177460.4 | Q12: 47768.332 | R12: 120818.87 | S12: 10238.888 | T12: =ROUND($O$12,2) -> 8873.02 | U12: =ROUND($O$12,2) -> 8873.02 | V12: =ROUND($O$12,2) -> 8873.02 | W12: =ROUND($O$12,2) -> 8873.02 | X12: 10238.888 | Y12: 4861.914 | Z12: =X12 -> 10238.888 | AA12: =Y12 -> 4861.914 | AB12: =Z12 -> 10238.888 | AC12: =AA12 -> 4861.914 | AD12: =AB12 -> 10238.888 | AE12: =AC12 -> 4861.914 | AF12: =AD12 -> 10238.888 | AG12: 4861.91 | AH12: 10238.888 | AI12: 4861.91 | AJ12: 10238.89 | AK12: 4861.91 | AL12: 10238.89 | AM12: 4861.91 | AN12: =SUM(T12:AM12) -> 156298.48 | AP12: =P12+AN12-AO12 -> 333758.88 | AQ12: =M12-AP12 -> 198622.07 | AS12: =IF(AQ12>H12,(AL12+AM12),0) -> 15100.8 | AT12: =IF(AS12+IF(AS12="0","0",AS12)>$AQ12,0,AS12) -> 15100.8 | AU12: =IF(SUM($AS$12:AT12)+IF(AT12="0","0",AT12)>$AQ12,0,AT12) -> 15100.8 | AV12: =IF(SUM($AS$12:AU12)+IF(AU12="0","0",AU12)>$AQ12,0,AU12) -> 15100.8 | AW12: =IF(SUM($AS$12:AV12)+IF(AV12="0","0",AV12)>$AQ12,0,AV12) -> 15100.8 | AX12: =IF(SUM($AS$12:AW12)+IF(AW12="0","0",AW12)>$AQ12,0,AW12) -> 15100.8 | AY12: =IF(SUM($AS$12:AX12)+IF(AX12="0","0",AX12)>$AQ12,0,AX12) -> 15100.8 | AZ12: =IF(SUM($AS$12:AY12)+IF(AY12="0","0",AY12)>$AQ12,0,AY12) -> 15100.8 | BA12: =IF(SUM($AS$12:AZ12)+IF(AZ12="0","0",AZ12)>$AQ12,0,AZ12) -> 15100.8 | BB12: =IF(SUM($AS$12:BA12)+IF(BA12="0","0",BA12)>$AQ12,0,BA12) -> 15100.8 | ... CN12: =IF(SUM($AS$12:CM12)+IF(CM12="0","0",CM12)>$AQ12,0,CM12) -> 0
A13: 8 | B13: Mercedes S-Class | C13: L 95118 | E13: 44705 | G13: 532380.95 | H13: =G13*30% -> 159714.28 | I13: =G13*70% -> 372666.66 | J13: 532380.95 | M13: =J13+K13-L13 -> 532380.95 | N13: =G13*20% -> 106476.19 | O13: =ROUND(N13/12,2) -> 8873.02 | P13: 170657.75 | Q13: 43339.932 | R13: 132049.92 | S13: 10236.428 | T13: =ROUND($O$13,2) -> 8873.02 | U13: =ROUND($O$13,2) -> 8873.02 | V13: =ROUND($O$13,2) -> 8873.02 | W13: =ROUND($O$13,2) -> 8873.02 | X13: 10236.428 | Y13: 4308.364 | Z13: =X13 -> 10236.428 | AA13: =Y13 -> 4308.364 | AB13: =Z13 -> 10236.428 | AC13: =AA13 -> 4308.364 | AD13: =AB13 -> 10236.428 | AE13: =AC13 -> 4308.364 | AF13: =AD13 -> 10236.428 | AG13: 4308.36 | AH13: 10236.428 | AI13: 4308.36 | AJ13: 10236.43 | AK13: 4308.36 | AL13: 10236.43 | AM13: 4308.36 | AN13: =SUM(T13:AM13) -> 151850.4 | AP13: =P13+AN13-AO13 -> 322508.15 | AQ13: =M13-AP13 -> 209872.8 | AS13: =IF(AQ13>H13,(AL13+AM13),0) -> 14544.79 | AT13: =IF(AS13+IF(AS13="0","0",AS13)>$AQ13,0,AS13) -> 14544.79 | AU13: =IF(SUM($AS$13:AT13)+IF(AT13="0","0",AT13)>$AQ13,0,AT13) -> 14544.79 | AV13: =IF(SUM($AS$13:AU13)+IF(AU13="0","0",AU13)>$AQ13,0,AU13) -> 14544.79 | AW13: =IF(SUM($AS$13:AV13)+IF(AV13="0","0",AV13)>$AQ13,0,AV13) -> 14544.79 | AX13: =IF(SUM($AS$13:AW13)+IF(AW13="0","0",AW13)>$AQ13,0,AW13) -> 14544.79 | AY13: =IF(SUM($AS$13:AX13)+IF(AX13="0","0",AX13)>$AQ13,0,AX13) -> 14544.79 | AZ13: =IF(SUM($AS$13:AY13)+IF(AY13="0","0",AY13)>$AQ13,0,AY13) -> 14544.79 | BA13: =IF(SUM($AS$13:AZ13)+IF(AZ13="0","0",AZ13)>$AQ13,0,AZ13) -> 14544.79 | BB13: =IF(SUM($AS$13:BA13)+IF(BA13="0","0",BA13)>$AQ13,0,BA13) -> 14544.79 | ... CN13: =IF(SUM($AS$13:CM13)+IF(CM13="0","0",CM13)>$AQ13,0,CM13) -> 0
A14: 9 | B14: Mercedes S-Class | C14: L 23269 | E14: 44719 | G14: 532380.95 | H14: =G14*30% -> 159714.28 | I14: =G14*70% -> 372666.66 | J14: 532380.95 | M14: =J14+K14-L14 -> 532380.95 | N14: =G14*20% -> 106476.19 | O14: =ROUND(N14/12,2) -> 8873.02 | P14: 166517.01 | Q14: 42715.984 | R14: 136814.61 | S14: 10235.507 | T14: =ROUND($O$14,2) -> 8873.02 | U14: =ROUND($O$14,2) -> 8873.02 | V14: =ROUND($O$14,2) -> 8873.02 | W14: =ROUND($O$14,2) -> 8873.02 | X14: 10235.507 | Y14: 4230.3705 | Z14: =X14 -> 10235.507 | AA14: =Y14 -> 4230.3705 | AB14: =Z14 -> 10235.507 | AC14: =AA14 -> 4230.3705 | AD14: =AB14 -> 10235.507 | AE14: =AC14 -> 4230.3705 | AF14: =AD14 -> 10235.507 | AG14: 4230.37 | AH14: 10235.507 | AI14: 4230.37 | AJ14: 10235.51 | AK14: 4230.37 | AL14: 10235.51 | AM14: 4230.37 | AN14: =SUM(T14:AM14) -> 151219.1 | AP14: =P14+AN14-AO14 -> 317736.11 | AQ14: =M14-AP14 -> 214644.84 | AS14: =IF(AQ14>H14,(AL14+AM14),0) -> 14465.88 | AT14: =IF(AS14+IF(AS14="0","0",AS14)>$AQ14,0,AS14) -> 14465.88 | AU14: =IF(SUM($AS$14:AT14)+IF(AT14="0","0",AT14)>$AQ14,0,AT14) -> 14465.88 | AV14: =IF(SUM($AS$14:AU14)+IF(AU14="0","0",AU14)>$AQ14,0,AU14) -> 14465.88 | AW14: =IF(SUM($AS$14:AV14)+IF(AV14="0","0",AV14)>$AQ14,0,AV14) -> 14465.88 | AX14: =IF(SUM($AS$14:AW14)+IF(AW14="0","0",AW14)>$AQ14,0,AW14) -> 14465.88 | AY14: =IF(SUM($AS$14:AX14)+IF(AX14="0","0",AX14)>$AQ14,0,AX14) -> 14465.88 | AZ14: =IF(SUM($AS$14:AY14)+IF(AY14="0","0",AY14)>$AQ14,0,AY14) -> 14465.88 | BA14: =IF(SUM($AS$14:AZ14)+IF(AZ14="0","0",AZ14)>$AQ14,0,AZ14) -> 14465.88 | BB14: =IF(SUM($AS$14:BA14)+IF(BA14="0","0",BA14)>$AQ14,0,BA14) -> 14465.88 | ... CN14: =IF(SUM($AS$14:CM14)+IF(CM14="0","0",CM14)>$AQ14,0,CM14) -> 0
A15: 10 | B15: Mercedes S-Class | C15: L 21982 | E15: 44769 | G15: 532380.95 | H15: =G15*30% -> 159714.28 | I15: =G15*70% -> 372666.66 | J15: 532380.95 | M15: =J15+K15-L15 -> 532380.95 | N15: =G15*20% -> 106476.19 | O15: =ROUND(N15/12,2) -> 8873.02 | P15: 150841.34 | Q15: 41374.911 | R15: 153831.35 | S15: 10232.684 | T15: =ROUND($O$15,2) -> 8873.02 | U15: =ROUND($O$15,2) -> 8873.02 | V15: =ROUND($O$15,2) -> 8873.02 | W15: =ROUND($O$15,2) -> 8873.02 | X15: 10232.684 | Y15: 4062.7364 | Z15: =X15 -> 10232.684 | AA15: =Y15 -> 4062.7364 | AB15: =Z15 -> 10232.684 | AC15: =AA15 -> 4062.7364 | AD15: =AB15 -> 10232.684 | AE15: =AC15 -> 4062.7364 | AF15: =AD15 -> 10232.684 | AG15: 4062.74 | AH15: 10232.684 | AI15: 4062.74 | AJ15: 10232.68 | AK15: 4062.74 | AL15: 10232.68 | AM15: 4062.74 | AN15: =SUM(T15:AM15) -> 149855.45 | AP15: =P15+AN15-AO15 -> 300696.79 | AQ15: =M15-AP15 -> 231684.16 | AS15: =IF(AQ15>H15,(AL15+AM15),0) -> 14295.42 | AT15: =IF(AS15+IF(AS15="0","0",AS15)>$AQ15,0,AS15) -> 14295.42 | AU15: =IF(SUM($AS$15:AT15)+IF(AT15="0","0",AT15)>$AQ15,0,AT15) -> 14295.42 | AV15: =IF(SUM($AS$15:AU15)+IF(AU15="0","0",AU15)>$AQ15,0,AU15) -> 14295.42 | AW15: =IF(SUM($AS$15:AV15)+IF(AV15="0","0",AV15)>$AQ15,0,AV15) -> 14295.42 | AX15: =IF(SUM($AS$15:AW15)+IF(AW15="0","0",AW15)>$AQ15,0,AW15) -> 14295.42 | AY15: =IF(SUM($AS$15:AX15)+IF(AX15="0","0",AX15)>$AQ15,0,AX15) -> 14295.42 | AZ15: =IF(SUM($AS$15:AY15)+IF(AY15="0","0",AY15)>$AQ15,0,AY15) -> 14295.42 | BA15: =IF(SUM($AS$15:AZ15)+IF(AZ15="0","0",AZ15)>$AQ15,0,AZ15) -> 14295.42 | BB15: =IF(SUM($AS$15:BA15)+IF(BA15="0","0",BA15)>$AQ15,0,BA15) -> 14295.42 | ... CN15: =IF(SUM($AS$15:CM15)+IF(CM15="0","0",CM15)>$AQ15,0,CM15) -> 0
A16: 11 | B16: Mercedes V-Class | C16: L 23872 | E16: 44833 | G16: 238095.24 | H16: =G16*30% -> 71428.572 | I16: =G16*70% -> 166666.67 | J16: 238095.24 | M16: =J16+K16-L16 -> 238095.24 | N16: =G16*20% -> 47619.048 | O16: =ROUND(N16/12,2) -> 3968.25 | P16: 59523.75 | Q16: 16699.355 | R16: 78538.813 | S16: 4575.0765 | T16: =ROUND($O$16,2) -> 3968.25 | U16: =ROUND($O$16,2) -> 3968.25 | V16: =ROUND($O$16,2) -> 3968.25 | W16: =ROUND($O$16,2) -> 3968.25 | X16: 4575.0765 | Y16: 1591.3881 | Z16: =X16 -> 4575.0765 | AA16: =Y16 -> 1591.3881 | AB16: =Z16 -> 4575.0765 | AC16: =AA16 -> 1591.3881 | AD16: =AB16 -> 4575.0765 | AE16: =AC16 -> 1591.3881 | AF16: =AD16 -> 4575.0765 | AG16: 1591.39 | AH16: 4575.0765 | AI16: 1591.39 | AJ16: 4575.08 | AK16: 1591.39 | AL16: 4575.08 | AM16: 1591.39 | AN16: =SUM(T16:AM16) -> 65204.731 | AP16: =P16+AN16-AO16 -> 124728.48 | AQ16: =M16-AP16 -> 113366.76 | AS16: =IF(AQ16>H16,(AL16+AM16),0) -> 6166.47 | AT16: =IF(AS16+IF(AS16="0","0",AS16)>$AQ16,0,AS16) -> 6166.47 | AU16: =IF(SUM($AS$16:AT16)+IF(AT16="0","0",AT16)>$AQ16,0,AT16) -> 6166.47 | AV16: =IF(SUM($AS$16:AU16)+IF(AU16="0","0",AU16)>$AQ16,0,AU16) -> 6166.47 | AW16: =IF(SUM($AS$16:AV16)+IF(AV16="0","0",AV16)>$AQ16,0,AV16) -> 6166.47 | AX16: =IF(SUM($AS$16:AW16)+IF(AW16="0","0",AW16)>$AQ16,0,AW16) -> 6166.47 | AY16: =IF(SUM($AS$16:AX16)+IF(AX16="0","0",AX16)>$AQ16,0,AX16) -> 6166.47 | AZ16: =IF(SUM($AS$16:AY16)+IF(AY16="0","0",AY16)>$AQ16,0,AY16) -> 6166.47 | BA16: =IF(SUM($AS$16:AZ16)+IF(AZ16="0","0",AZ16)>$AQ16,0,AZ16) -> 6166.47 | BB16: =IF(SUM($AS$16:BA16)+IF(BA16="0","0",BA16)>$AQ16,0,BA16) -> 6166.47 | ... CN16: =IF(SUM($AS$16:CM16)+IF(CM16="0","0",CM16)>$AQ16,0,CM16) -> 0
A17: 12 | B17: Mercedes V-Class | C17: L 25149 | E17: 45007 | G17: 219047.62 | H17: =G17*30% -> 65714.286 | I17: =G17*70% -> 153333.33 | J17: 219048 | M17: =J17+K17-L17 -> 219048 | N17: =G17*20% -> 43809.524 | O17: =ROUND(N17/12,2) -> 3650.79 | P17: 32857.11 | Q17: 12902.849 | R17: 96621.005 | S17: 4207.0104 | T17: =ROUND($O$17,2) -> 3650.79 | U17: =ROUND($O$17,2) -> 3650.79 | V17: =ROUND($O$17,2) -> 3650.79 | W17: =ROUND($O$17,2) -> 3650.79 | X17: 4207.0104 | Y17: 1156.5074 | Z17: =X17 -> 4207.0104 | AA17: =Y17 -> 1156.5074 | AB17: =Z17 -> 4207.0104 | AC17: =AA17 -> 1156.5074 | AD17: =AB17 -> 4207.0104 | AE17: =AC17 -> 1156.5074 | AF17: =AD17 -> 4207.0104 | AG17: 1156.51 | AH17: 4207.0104 | AI17: 1156.51 | AJ17: 4207.01 | AK17: 1156.51 | AL17: 4207.01 | AM17: 1156.51 | AN17: =SUM(T17:AM17) -> 57511.312 | AP17: =P17+AN17-AO17 -> 90368.422 | AQ17: =M17-AP17 -> 128679.58 | AS17: =IF(AQ17>H17,(AL17+AM17),0) -> 5363.52 | AT17: =IF(AS17+IF(AS17="0","0",AS17)>$AQ17,0,AS17) -> 5363.52 | AU17: =IF(SUM($AS$17:AT17)+IF(AT17="0","0",AT17)>$AQ17,0,AT17) -> 5363.52 | AV17: =IF(SUM($AS$17:AU17)+IF(AU17="0","0",AU17)>$AQ17,0,AU17) -> 5363.52 | AW17: =IF(SUM($AS$17:AV17)+IF(AV17="0","0",AV17)>$AQ17,0,AV17) -> 5363.52 | AX17: =IF(SUM($AS$17:AW17)+IF(AW17="0","0",AW17)>$AQ17,0,AW17) -> 5363.52 | AY17: =IF(SUM($AS$17:AX17)+IF(AX17="0","0",AX17)>$AQ17,0,AX17) -> 5363.52 | AZ17: =IF(SUM($AS$17:AY17)+IF(AY17="0","0",AY17)>$AQ17,0,AY17) -> 5363.52 | BA17: =IF(SUM($AS$17:AZ17)+IF(AZ17="0","0",AZ17)>$AQ17,0,AZ17) -> 5363.52 | BB17: =IF(SUM($AS$17:BA17)+IF(BA17="0","0",BA17)>$AQ17,0,BA17) -> 5363.52 | ... CN17: =IF(SUM($AS$17:CM17)+IF(CM17="0","0",CM17)>$AQ17,0,CM17) -> 0
A18: 13 | B18: Mercedes EQS | C18: L 25144 | E18: 45061 | G18: 561102.33 | H18: =G18*30% -> 168330.7 | I18: =G18*70% -> 392771.63 | J18: 561102.33 | M18: =J18+K18-L18 -> 561102.33 | N18: =G18*20% -> 112220.47 | O18: =ROUND(N18/12,2) -> 9351.71 | P18: 70288.659 | Q18: 27558.35 | R18: 266869.49 | S18: 10775.35 | T18: =ROUND(O18,2) -> 9351.71 | U18: =ROUND($O$18,2) -> 9351.71 | V18: =ROUND($O$18,2) -> 9351.71 | W18: =ROUND($O$18,2) -> 9351.71 | X18: 10775.35 | Y18: 2275.83 | Z18: =X18 -> 10775.35 | AA18: =Y18 -> 2275.83 | AB18: =Z18 -> 10775.35 | AC18: =AA18 -> 2275.83 | AD18: =AB18 -> 10775.35 | AE18: =AC18 -> 2275.83 | AF18: =AD18 -> 10775.35 | AG18: 2275.83 | AH18: 10775.35 | AI18: 2275.83 | AJ18: 10775.35 | AK18: 2275.83 | AL18: 10775.35 | AM18: 2275.83 | AN18: =SUM(T18:AM18) -> 141816.28 | AP18: =P18+AN18-AO18 -> 212104.94 | AQ18: =M18-AP18 -> 348997.39 | AS18: =IF(AQ18>H18,(AL18+AM18),0) -> 13051.18 | AT18: =IF(AS18+IF(AS18="0","0",AS18)>$AQ18,0,AS18) -> 13051.18 | AU18: =IF(SUM($AS$18:AT18)+IF(AT18="0","0",AT18)>$AQ18,0,AT18) -> 13051.18 | AV18: =IF(SUM($AS$18:AU18)+IF(AU18="0","0",AU18)>$AQ18,0,AU18) -> 13051.18 | AW18: =IF(SUM($AS$18:AV18)+IF(AV18="0","0",AV18)>$AQ18,0,AV18) -> 13051.18 | AX18: =IF(SUM($AS$18:AW18)+IF(AW18="0","0",AW18)>$AQ18,0,AW18) -> 13051.18 | AY18: =IF(SUM($AS$18:AX18)+IF(AX18="0","0",AX18)>$AQ18,0,AX18) -> 13051.18 | AZ18: =IF(SUM($AS$18:AY18)+IF(AY18="0","0",AY18)>$AQ18,0,AY18) -> 13051.18 | BA18: =IF(SUM($AS$18:AZ18)+IF(AZ18="0","0",AZ18)>$AQ18,0,AZ18) -> 13051.18 | BB18: =IF(SUM($AS$18:BA18)+IF(BA18="0","0",BA18)>$AQ18,0,BA18) -> 13051.18 | ... CN18: =IF(SUM($AS$18:CM18)+IF(CM18="0","0",CM18)>$AQ18,0,CM18) -> 0
A19: 14 | B19: Mercedes EQS 450 Plus | C19: L 25156 | E19: 45093 | G19: 561052.4 | H19: =G19*30% -> 168315.72 | I19: =G19*70% -> 392736.68 | J19: 561052.4 | M19: =J19+K19-L19 -> 561052.4 | N19: =G19*20% -> 112210.48 | O19: =ROUND(N19/12,2) -> 9350.87 | P19: 60468.959 | Q19: 25892.13 | R19: 278322.98 | S19: 10773.793 | T19: =ROUND($O$19,2) -> 9350.87 | U19: =ROUND($O$19,2) -> 9350.87 | V19: =ROUND($O$19,2) -> 9350.87 | W19: =ROUND($O$19,2) -> 9350.87 | X19: 10773.793 | Y19: 2067.6575 | Z19: =X19 -> 10773.793 | AA19: =Y19 -> 2067.6575 | AB19: =Z19 -> 10773.793 | AC19: =AA19 -> 2067.6575 | AD19: =AB19 -> 10773.793 | AE19: =AC19 -> 2067.6575 | AF19: =AD19 -> 10773.793 | AG19: 2067.66 | AH19: 10773.793 | AI19: 2067.66 | AJ19: 10773.79 | AK19: 2067.66 | AL19: 10773.79 | AM19: 2067.66 | AN19: =SUM(T19:AM19) -> 140135.09 | AP19: =P19+AN19-AO19 -> 200604.05 | AQ19: =M19-AP19 -> 360448.35 | AS19: =IF(AQ19>H19,(AL19+AM19),0) -> 12841.45 | AT19: =IF(AS19+IF(AS19="0","0",AS19)>$AQ19,0,AS19) -> 12841.45 | AU19: =IF(SUM($AS$19:AT19)+IF(AT19="0","0",AT19)>$AQ19,0,AT19) -> 12841.45 | AV19: =IF(SUM($AS$19:AU19)+IF(AU19="0","0",AU19)>$AQ19,0,AU19) -> 12841.45 | AW19: =IF(SUM($AS$19:AV19)+IF(AV19="0","0",AV19)>$AQ19,0,AV19) -> 12841.45 | AX19: =IF(SUM($AS$19:AW19)+IF(AW19="0","0",AW19)>$AQ19,0,AW19) -> 12841.45 | AY19: =IF(SUM($AS$19:AX19)+IF(AX19="0","0",AX19)>$AQ19,0,AX19) -> 12841.45 | AZ19: =IF(SUM($AS$19:AY19)+IF(AY19="0","0",AY19)>$AQ19,0,AY19) -> 12841.45 | BA19: =IF(SUM($AS$19:AZ19)+IF(AZ19="0","0",AZ19)>$AQ19,0,AZ19) -> 12841.45 | BB19: =IF(SUM($AS$19:BA19)+IF(BA19="0","0",BA19)>$AQ19,0,BA19) -> 12841.45 | ... CN19: =IF(SUM($AS$19:CM19)+IF(CM19="0","0",CM19)>$AQ19,0,CM19) -> 0
A20: 15 | B20: Mercedes 450M Saloon | C20: L 25161 | E20: 45093 | G20: 542957.2 | H20: =G20*30% -> 162887.16 | I20: =G20*70% -> 380070.04 | J20: 542957.2 | M20: =J20+K20-L20 -> 542957.2 | N20: =G20*20% -> 108591.44 | O20: =ROUND(N20/12,2) -> 9049.29 | P20: 58518.742 | Q20: 25056.989 | R20: 269346.44 | S20: 10426.314 | T20: =ROUND($O$20,2) -> 9049.29 | U20: =ROUND($O$20,2) -> 9049.29 | V20: =ROUND($O$20,2) -> 9049.29 | W20: =ROUND($O$20,2) -> 9049.29 | X20: 10426.314 | Y20: 2000.9623 | Z20: =X20 -> 10426.314 | AA20: =Y20 -> 2000.9623 | AB20: =Z20 -> 10426.314 | AC20: =AA20 -> 2000.9623 | AD20: =AB20 -> 10426.314 | AE20: =AC20 -> 2000.9623 | AF20: =AD20 -> 10426.314 | AG20: 2000.96 | AH20: 10426.314 | AI20: 2000.96 | AJ20: 10426.31 | AK20: 2000.96 | AL20: 10426.31 | AM20: 2000.96 | AN20: =SUM(T20:AM20) -> 135615.35 | AP20: =P20+AN20-AO20 -> 194134.09 | AQ20: =M20-AP20 -> 348823.11 | AS20: =IF(AQ20>H20,(AL20+AM20),0) -> 12427.27 | AT20: =IF(AS20+IF(AS20="0","0",AS20)>$AQ20,0,AS20) -> 12427.27 | AU20: =IF(SUM($AS$20:AT20)+IF(AT20="0","0",AT20)>$AQ20,0,AT20) -> 12427.27 | AV20: =IF(SUM($AS$20:AU20)+IF(AU20="0","0",AU20)>$AQ20,0,AU20) -> 12427.27 | AW20: =IF(SUM($AS$20:AV20)+IF(AV20="0","0",AV20)>$AQ20,0,AV20) -> 12427.27 | AX20: =IF(SUM($AS$20:AW20)+IF(AW20="0","0",AW20)>$AQ20,0,AW20) -> 12427.27 | AY20: =IF(SUM($AS$20:AX20)+IF(AX20="0","0",AX20)>$AQ20,0,AX20) -> 12427.27 | AZ20: =IF(SUM($AS$20:AY20)+IF(AY20="0","0",AY20)>$AQ20,0,AY20) -> 12427.27 | BA20: =IF(SUM($AS$20:AZ20)+IF(AZ20="0","0",AZ20)>$AQ20,0,AZ20) -> 12427.27 | BB20: =IF(SUM($AS$20:BA20)+IF(BA20="0","0",BA20)>$AQ20,0,BA20) -> 12427.27 | ... CN20: =IF(SUM($AS$20:CM20)+IF(CM20="0","0",CM20)>$AQ20,0,CM20) -> 0
A21: 16 | B21: Mercedes V-Class | C21: L 29681 | E21: 45168 | G21: 352380.95 | H21: =G21*30% -> 105714.29 | I21: =G21*70% -> 246666.66 | J21: 352380.95 | M21: =J21+K21-L21 -> 352380.95 | N21: =G21*20% -> 70476.19 | O21: =ROUND(N21/12,2) -> 5873.02 | P21: 23681.532 | Q21: 13664.4 | R21: 191701.67 | S21: 6765.9414 | T21: =ROUND($O$21,2) -> 5873.02 | U21: =ROUND($O$21,2) -> 5873.02 | V21: =ROUND($O$21,2) -> 5873.02 | W21: =ROUND($O$21,2) -> 5873.02 | X21: 6765.9414 | Y21: 973.92247 | Z21: =X21 -> 6765.9414 | AA21: =Y21 -> 973.92247 | AB21: =Z21 -> 6765.9414 | AC21: =AA21 -> 973.92247 | AD21: =AB21 -> 6765.9414 | AE21: =AC21 -> 973.92247 | AF21: =AD21 -> 6765.9414 | AG21: 973.92 | AH21: 6765.9414 | AI21: 973.92 | AJ21: 6765.94 | AK21: 973.92 | AL21: 6765.94 | AM21: 973.92 | AN21: =SUM(T21:AM21) -> 85410.978 | AP21: =P21+AN21-AO21 -> 109092.51 | AQ21: =M21-AP21 -> 243288.44 | AS21: =IF(AQ21>H21,(AL21+AM21),0) -> 7739.86 | AT21: =IF(AS21+IF(AS21="0","0",AS21)>$AQ21,0,AS21) -> 7739.86 | AU21: =IF(SUM($AS$21:AT21)+IF(AT21="0","0",AT21)>$AQ21,0,AT21) -> 7739.86 | AV21: =IF(SUM($AS$21:AU21)+IF(AU21="0","0",AU21)>$AQ21,0,AU21) -> 7739.86 | AW21: =IF(SUM($AS$21:AV21)+IF(AV21="0","0",AV21)>$AQ21,0,AV21) -> 7739.86 | AX21: =IF(SUM($AS$21:AW21)+IF(AW21="0","0",AW21)>$AQ21,0,AW21) -> 7739.86 | AY21: =IF(SUM($AS$21:AX21)+IF(AX21="0","0",AX21)>$AQ21,0,AX21) -> 7739.86 | AZ21: =IF(SUM($AS$21:AY21)+IF(AY21="0","0",AY21)>$AQ21,0,AY21) -> 7739.86 | BA21: =IF(SUM($AS$21:AZ21)+IF(AZ21="0","0",AZ21)>$AQ21,0,AZ21) -> 7739.86 | BB21: =IF(SUM($AS$21:BA21)+IF(BA21="0","0",BA21)>$AQ21,0,BA21) -> 7739.86 | ... CN21: =IF(SUM($AS$21:CM21)+IF(CM21="0","0",CM21)>$AQ21,0,CM21) -> 0
A22: 17 | B22: Maybach | C22: L 25417 | E22: 45183 | G22: 1093758.7 | H22: =G22*30% -> 328127.6 | I22: =G22*70% -> 765631.08 | J22: 1300229.2 | M22: =J22+K22-L22 -> 1300229.2 | N22: =G22*20% -> 218751.74 | O22: =ROUND(N22/12,2) -> 18229.31 | P22: 76569 | Q22: 28861.35 | R22: 605512.8 | S22: 21000.444 | T22: =ROUND($O$22,2) -> 18229.31 | U22: =ROUND($O$22,2) -> 18229.31 | V22: =ROUND($O$22,2) -> 18229.31 | W22: =ROUND($O$22,2) -> 18229.31 | X22: 21000.444 | Y22: 1329.005 | Z22: =X22 -> 21000.444 | AA22: =Y22 -> 1329.005 | AB22: =Z22 -> 21000.444 | AC22: =AA22 -> 1329.005 | AD22: =AB22 -> 21000.444 | AE22: =AC22 -> 1329.005 | AF22: =AD22 -> 21000.444 | AG22: 1329 | AH22: 21000.444 | AI22: 1329 | AJ22: 21000.44 | AK22: 1329 | AL22: 21000.44 | AM22: 1329 | AN22: =SUM(T22:AM22) -> 251552.8 | AP22: =P22+AN22-AO22 -> 328121.8 | AQ22: =M22-AP22 -> 972107.38 | AS22: =IF(AQ22>H22,(AL22+AM22),0) -> 22329.44 | AT22: =IF(AS22+IF(AS22="0","0",AS22)>$AQ22,0,AS22) -> 22329.44 | AU22: =IF(SUM($AS$22:AT22)+IF(AT22="0","0",AT22)>$AQ22,0,AT22) -> 22329.44 | AV22: =IF(SUM($AS$22:AU22)+IF(AU22="0","0",AU22)>$AQ22,0,AU22) -> 22329.44 | AW22: =IF(SUM($AS$22:AV22)+IF(AV22="0","0",AV22)>$AQ22,0,AV22) -> 22329.44 | AX22: =IF(SUM($AS$22:AW22)+IF(AW22="0","0",AW22)>$AQ22,0,AW22) -> 22329.44 | AY22: =IF(SUM($AS$22:AX22)+IF(AX22="0","0",AX22)>$AQ22,0,AX22) -> 22329.44 | AZ22: =IF(SUM($AS$22:AY22)+IF(AY22="0","0",AY22)>$AQ22,0,AY22) -> 22329.44 | BA22: =IF(SUM($AS$22:AZ22)+IF(AZ22="0","0",AZ22)>$AQ22,0,AZ22) -> 22329.44 | BB22: =IF(SUM($AS$22:BA22)+IF(BA22="0","0",BA22)>$AQ22,0,BA22) -> 22329.44 | ... CN22: =IF(SUM($AS$22:CM22)+IF(CM22="0","0",CM22)>$AQ22,0,CM22) -> 0
A23: 18 | B23: Mercedes V-Class | C23: L 25660 | E23: 45223 | G23: 449797 | H23: =G23*30% -> 134939.1 | I23: =G23*70% -> 314857.9 | J23: 449797 | M23: =J23+K23-L23 -> 449797 | N23: =G23*20% -> 89959.4 | O23: =ROUND(N23/12,2) -> 7496.62 | P23: 16444.199 | Q23: 15411.277 | R23: 260512.56 | S23: 8635.7756 | T23: =ROUND($O$23,2) -> 7496.62 | U23: =ROUND($O$23,2) -> 7496.62 | V23: =ROUND($O$23,2) -> 7496.62 | W23: =ROUND($O$23,2) -> 7496.62 | X23: 8635.7756 | Y23: 989.33218 | Z23: =X23 -> 8635.7756 | AA23: =Y23 -> 989.33218 | AB23: =Z23 -> 8635.7756 | AC23: =AA23 -> 989.33218 | AD23: =AB23 -> 8635.7756 | AE23: =AC23 -> 989.33218 | AF23: =AD23 -> 8635.7756 | AG23: 989.33 | AH23: 8635.7756 | AI23: 989.33 | AJ23: 8635.78 | AK23: 989.33 | AL23: 8635.78 | AM23: 989.33 | AN23: =SUM(T23:AM23) -> 106987.34 | AP23: =P23+AN23-AO23 -> 123431.54 | AQ23: =M23-AP23 -> 326365.46 | AS23: =IF(AQ23>H23,(AL23+AM23),0) -> 9625.11 | AT23: =IF(AS23+IF(AS23="0","0",AS23)>$AQ23,0,AS23) -> 9625.11 | AU23: =IF(SUM($AS$23:AT23)+IF(AT23="0","0",AT23)>$AQ23,0,AT23) -> 9625.11 | AV23: =IF(SUM($AS$23:AU23)+IF(AU23="0","0",AU23)>$AQ23,0,AU23) -> 9625.11 | AW23: =IF(SUM($AS$23:AV23)+IF(AV23="0","0",AV23)>$AQ23,0,AV23) -> 9625.11 | AX23: =IF(SUM($AS$23:AW23)+IF(AW23="0","0",AW23)>$AQ23,0,AW23) -> 9625.11 | AY23: =IF(SUM($AS$23:AX23)+IF(AX23="0","0",AX23)>$AQ23,0,AX23) -> 9625.11 | AZ23: =IF(SUM($AS$23:AY23)+IF(AY23="0","0",AY23)>$AQ23,0,AY23) -> 9625.11 | BA23: =IF(SUM($AS$23:AZ23)+IF(AZ23="0","0",AZ23)>$AQ23,0,AZ23) -> 9625.11 | BB23: =IF(SUM($AS$23:BA23)+IF(BA23="0","0",BA23)>$AQ23,0,BA23) -> 9625.11 | ... CN23: =IF(SUM($AS$23:CM23)+IF(CM23="0","0",CM23)>$AQ23,0,CM23) -> 0
A24: 19 | B24: Mercedes V-Class | C24: L 25310 | E24: 45225 | G24: 433333 | H24: =G24*30% -> 129999.9 | I24: =G24*70% -> 303333.1 | J24: 433333 | M24: =J24+K24-L24 -> 433333 | N24: =G24*20% -> 86666.6 | O24: =ROUND(N24/12,2) -> 7222.22 | P24: 15376.339 | Q24: 14759.092 | R24: 251531.01 | S24: 8319.6585 | T24: =ROUND($O$24,2) -> 7222.22 | U24: =ROUND($O$24,2) -> 7222.22 | V24: =ROUND($O$24,2) -> 7222.22 | W24: =ROUND($O$24,2) -> 7222.22 | X24: 8319.6585 | Y24: 942.10896 | Z24: =X24 -> 8319.6585 | AA24: =Y24 -> 942.10896 | AB24: =Z24 -> 8319.6585 | AC24: =AA24 -> 942.10896 | AD24: =AB24 -> 8319.6585 | AE24: =AC24 -> 942.10896 | AF24: =AD24 -> 8319.6585 | AG24: 942.11 | AH24: 8319.6585 | AI24: 942.11 | AJ24: 8319.66 | AK24: 942.11 | AL24: 8319.66 | AM24: 942.11 | AN24: =SUM(T24:AM24) -> 102983.03 | AP24: =P24+AN24-AO24 -> 118359.37 | AQ24: =M24-AP24 -> 314973.63 | AS24: =IF(AQ24>H24,(AL24+AM24),0) -> 9261.77 | AT24: =IF(AS24+IF(AS24="0","0",AS24)>$AQ24,0,AS24) -> 9261.77 | AU24: =IF(SUM($AS$24:AT24)+IF(AT24="0","0",AT24)>$AQ24,0,AT24) -> 9261.77 | AV24: =IF(SUM($AS$24:AU24)+IF(AU24="0","0",AU24)>$AQ24,0,AU24) -> 9261.77 | AW24: =IF(SUM($AS$24:AV24)+IF(AV24="0","0",AV24)>$AQ24,0,AV24) -> 9261.77 | AX24: =IF(SUM($AS$24:AW24)+IF(AW24="0","0",AW24)>$AQ24,0,AW24) -> 9261.77 | AY24: =IF(SUM($AS$24:AX24)+IF(AX24="0","0",AX24)>$AQ24,0,AX24) -> 9261.77 | AZ24: =IF(SUM($AS$24:AY24)+IF(AY24="0","0",AY24)>$AQ24,0,AY24) -> 9261.77 | BA24: =IF(SUM($AS$24:AZ24)+IF(AZ24="0","0",AZ24)>$AQ24,0,AZ24) -> 9261.77 | BB24: =IF(SUM($AS$24:BA24)+IF(BA24="0","0",BA24)>$AQ24,0,BA24) -> 9261.77 | ... CN24: =IF(SUM($AS$24:CM24)+IF(CM24="0","0",CM24)>$AQ24,0,CM24) -> 0
A25: 20 | B25: Mercedes V-Class | C25: L 24236 | E25: 45230 | G25: 428571 | H25: =G25*30% -> 128571.3 | I25: =G25*70% -> 299999.7 | J25: 428571 | M25: =J25+K25-L25 -> 428571 | N25: =G25*20% -> 85714.2 | O25: =ROUND(N25/12,2) -> 7142.85 | P25: 14516.115 | Q25: 13918.299 | R25: 250136.74 | S25: 8228.1821 | T25: =ROUND($O$25,2) -> 7142.85 | U25: =ROUND($O$25,2) -> 7142.85 | V25: =ROUND($O$25,2) -> 7142.85 | W25: =ROUND($O$25,2) -> 7142.85 | X25: 8228.1821 | Y25: 846.93116 | Z25: =X25 -> 8228.1821 | AA25: =Y25 -> 846.93116 | AB25: =Z25 -> 8228.1821 | AC25: =AA25 -> 846.93116 | AD25: =AB25 -> 8228.1821 | AE25: =AC25 -> 846.93116 | AF25: =AD25 -> 8228.1821 | AG25: 846.93 | AH25: 8228.1821 | AI25: 846.93 | AJ25: 8228.18 | AK25: 846.93 | AL25: 8228.18 | AM25: 846.93 | AN25: =SUM(T25:AM25) -> 101172.3 | AP25: =P25+AN25-AO25 -> 115688.41 | AQ25: =M25-AP25 -> 312882.59 | AS25: =IF(AQ25>H25,(AL25+AM25),0) -> 9075.11 | AT25: =IF(AS25+IF(AS25="0","0",AS25)>$AQ25,0,AS25) -> 9075.11 | AU25: =IF(SUM($AS$25:AT25)+IF(AT25="0","0",AT25)>$AQ25,0,AT25) -> 9075.11 | AV25: =IF(SUM($AS$25:AU25)+IF(AU25="0","0",AU25)>$AQ25,0,AU25) -> 9075.11 | AW25: =IF(SUM($AS$25:AV25)+IF(AV25="0","0",AV25)>$AQ25,0,AV25) -> 9075.11 | AX25: =IF(SUM($AS$25:AW25)+IF(AW25="0","0",AW25)>$AQ25,0,AW25) -> 9075.11 | AY25: =IF(SUM($AS$25:AX25)+IF(AX25="0","0",AX25)>$AQ25,0,AX25) -> 9075.11 | AZ25: =IF(SUM($AS$25:AY25)+IF(AY25="0","0",AY25)>$AQ25,0,AY25) -> 9075.11 | BA25: =IF(SUM($AS$25:AZ25)+IF(AZ25="0","0",AZ25)>$AQ25,0,AZ25) -> 9075.11 | BB25: =IF(SUM($AS$25:BA25)+IF(BA25="0","0",BA25)>$AQ25,0,BA25) -> 9075.11 | ... CN25: =IF(SUM($AS$25:CM25)+IF(CM25="0","0",CM25)>$AQ25,0,CM25) -> 0
A26: 21 | B26: Mercedes S 500 | C26: L 29740 | E26: 45230 | G26: 627719 | H26: =G26*30% -> 188315.7 | I26: =G26*70% -> 439403.3 | J26: 627719 | M26: =J26+K26-L26 -> 627719 | N26: =G26*20% -> 125543.8 | O26: =ROUND(N26/12,2) -> 10461.98 | P26: 21261.443 | Q26: 20385.859 | R26: 366370.06 | S26: 12051.647 | T26: =ROUND($O$26,2) -> 10461.98 | U26: =ROUND($O$26,2) -> 10461.98 | V26: =ROUND($O$26,2) -> 10461.98 | W26: =ROUND($O$26,2) -> 10461.98 | X26: 12051.647 | Y26: 1240.4849 | Z26: =X26 -> 12051.647 | AA26: =Y26 -> 1240.4849 | AB26: =Z26 -> 12051.647 | AC26: =AA26 -> 1240.4849 | AD26: =AB26 -> 12051.647 | AE26: =AC26 -> 1240.4849 | AF26: =AD26 -> 12051.647 | AG26: 1240.48 | AH26: 12051.647 | AI26: 1240.48 | AJ26: 12051.65 | AK26: 1240.48 | AL26: 12051.65 | AM26: 1240.48 | AN26: =SUM(T26:AM26) -> 148184.96 | AP26: =P26+AN26-AO26 -> 169446.4 | AQ26: =M26-AP26 -> 458272.6 | AS26: =IF(AQ26>H26,(AL26+AM26),0) -> 13292.13 | AT26: =IF(AS26+IF(AS26="0","0",AS26)>$AQ26,0,AS26) -> 13292.13 | AU26: =IF(SUM($AS$26:AT26)+IF(AT26="0","0",AT26)>$AQ26,0,AT26) -> 13292.13 | AV26: =IF(SUM($AS$26:AU26)+IF(AU26="0","0",AU26)>$AQ26,0,AU26) -> 13292.13 | AW26: =IF(SUM($AS$26:AV26)+IF(AV26="0","0",AV26)>$AQ26,0,AV26) -> 13292.13 | AX26: =IF(SUM($AS$26:AW26)+IF(AW26="0","0",AW26)>$AQ26,0,AW26) -> 13292.13 | AY26: =IF(SUM($AS$26:AX26)+IF(AX26="0","0",AX26)>$AQ26,0,AX26) -> 13292.13 | AZ26: =IF(SUM($AS$26:AY26)+IF(AY26="0","0",AY26)>$AQ26,0,AY26) -> 13292.13 | BA26: =IF(SUM($AS$26:AZ26)+IF(AZ26="0","0",AZ26)>$AQ26,0,AZ26) -> 13292.13 | BB26: =IF(SUM($AS$26:BA26)+IF(BA26="0","0",BA26)>$AQ26,0,BA26) -> 13292.13 | ... CN26: =IF(SUM($AS$26:CM26)+IF(CM26="0","0",CM26)>$AQ26,0,CM26) -> 0
A27: 22 | B27: Mercedes S 500 | C27: L 25158 | E27: 45230 | G27: 627719 | H27: =G27*30% -> 188315.7 | I27: =G27*70% -> 439403.3 | J27: 627719 | M27: =J27+K27-L27 -> 627719 | N27: =G27*20% -> 125543.8 | O27: =ROUND(N27/12,2) -> 10461.98 | P27: 21261.443 | Q27: 20385.859 | R27: 366370.06 | S27: 12051.647 | T27: =ROUND($O$27,2) -> 10461.98 | U27: =ROUND($O$27,2) -> 10461.98 | V27: =ROUND($O$27,2) -> 10461.98 | W27: =ROUND($O$27,2) -> 10461.98 | X27: 12051.647 | Y27: 1240.4849 | Z27: =X27 -> 12051.647 | AA27: =Y27 -> 1240.4849 | AB27: =Z27 -> 12051.647 | AC27: =AA27 -> 1240.4849 | AD27: =AB27 -> 12051.647 | AE27: =AC27 -> 1240.4849 | AF27: =AD27 -> 12051.647 | AG27: 1240.48 | AH27: 12051.647 | AI27: 1240.48 | AJ27: 12051.65 | AK27: 1240.48 | AL27: 12051.65 | AM27: 1240.48 | AN27: =SUM(T27:AM27) -> 148184.96 | AP27: =P27+AN27-AO27 -> 169446.4 | AQ27: =M27-AP27 -> 458272.6 | AS27: =IF(AQ27>H27,(AL27+AM27),0) -> 13292.13 | AT27: =IF(AS27+IF(AS27="0","0",AS27)>$AQ27,0,AS27) -> 13292.13 | AU27: =IF(SUM($AS$27:AT27)+IF(AT27="0","0",AT27)>$AQ27,0,AT27) -> 13292.13 | AV27: =IF(SUM($AS$27:AU27)+IF(AU27="0","0",AU27)>$AQ27,0,AU27) -> 13292.13 | AW27: =IF(SUM($AS$27:AV27)+IF(AV27="0","0",AV27)>$AQ27,0,AV27) -> 13292.13 | AX27: =IF(SUM($AS$27:AW27)+IF(AW27="0","0",AW27)>$AQ27,0,AW27) -> 13292.13 | AY27: =IF(SUM($AS$27:AX27)+IF(AX27="0","0",AX27)>$AQ27,0,AX27) -> 13292.13 | AZ27: =IF(SUM($AS$27:AY27)+IF(AY27="0","0",AY27)>$AQ27,0,AY27) -> 13292.13 | BA27: =IF(SUM($AS$27:AZ27)+IF(AZ27="0","0",AZ27)>$AQ27,0,AZ27) -> 13292.13 | BB27: =IF(SUM($AS$27:BA27)+IF(BA27="0","0",BA27)>$AQ27,0,BA27) -> 13292.13 | ... CN27: =IF(SUM($AS$27:CM27)+IF(CM27="0","0",CM27)>$AQ27,0,CM27) -> 0
A28: 23 | B28: Mercedes Benz V class Avantgarde | C28: L 25173 | E28: 45240 | G28: 385714.29 | H28: =G28*30% -> 115714.29 | I28: =G28*70% -> 270000 | J28: 385714.29 | M28: =J28+K28-L28 -> 385714.29 | N28: =G28*20% -> 77142.858 | O28: =ROUND(N28/12,2) -> 6428.57 | P28: 10714.283 | Q28: 12410.966 | R28: 227589.04 | S28: 7405.2834 | T28: =ROUND($O$28,2) -> 6428.57 | U28: =ROUND($O$28,2) -> 6428.57 | V28: =ROUND($O$28,2) -> 6428.57 | W28: =ROUND($O$28,2) -> 6428.57 | X28: 7405.2834 | Y28: 747.79951 | Z28: =X28 -> 7405.2834 | AA28: =Y28 -> 747.79951 | AB28: =Z28 -> 7405.2834 | AC28: =AA28 -> 747.79951 | AD28: =AB28 -> 7405.2834 | AE28: =AC28 -> 747.79951 | AF28: =AD28 -> 7405.2834 | AG28: 747.8 | AH28: 7405.2834 | AI28: 747.8 | AJ28: 7405.28 | AK28: 747.8 | AL28: 7405.28 | AM28: 747.8 | AN28: =SUM(T28:AM28) -> 90938.939 | AP28: =P28+AN28-AO28 -> 101653.22 | AQ28: =M28-AP28 -> 284061.07 | AS28: =IF(AQ28>H28,(AL28+AM28),0) -> 8153.08 | AT28: =IF(AS28+IF(AS28="0","0",AS28)>$AQ28,0,AS28) -> 8153.08 | AU28: =IF(SUM($AS$28:AT28)+IF(AT28="0","0",AT28)>$AQ28,0,AT28) -> 8153.08 | AV28: =IF(SUM($AS$28:AU28)+IF(AU28="0","0",AU28)>$AQ28,0,AU28) -> 8153.08 | AW28: =IF(SUM($AS$28:AV28)+IF(AV28="0","0",AV28)>$AQ28,0,AV28) -> 8153.08 | AX28: =IF(SUM($AS$28:AW28)+IF(AW28="0","0",AW28)>$AQ28,0,AW28) -> 8153.08 | AY28: =IF(SUM($AS$28:AX28)+IF(AX28="0","0",AX28)>$AQ28,0,AX28) -> 8153.08 | AZ28: =IF(SUM($AS$28:AY28)+IF(AY28="0","0",AY28)>$AQ28,0,AY28) -> 8153.08 | BA28: =IF(SUM($AS$28:AZ28)+IF(AZ28="0","0",AZ28)>$AQ28,0,AZ28) -> 8153.08 | BB28: =IF(SUM($AS$28:BA28)+IF(BA28="0","0",BA28)>$AQ28,0,BA28) -> 8153.08 | ... CN28: =IF(SUM($AS$28:CM28)+IF(CM28="0","0",CM28)>$AQ28,0,CM28) -> 0
A29: 24 | B29: Mercedes Benz V class Avantgarde | C29: L 27891 | E29: 45260 | G29: 390476.19 | H29: =G29*30% -> 117142.86 | I29: =G29*70% -> 273333.33 | J29: 390476.19 | M29: =J29+K29-L29 -> 390476.19 | N29: =G29*20% -> 78095.238 | O29: =ROUND(N29/12,2) -> 6507.94 | P29: 6507.94 | Q29: 11910.401 | R29: 235391.17 | S29: 7496.5341 | T29: =ROUND($O$29,2) -> 6507.94 | U29: =ROUND($O$29,2) -> 6507.94 | V29: =ROUND($O$29,2) -> 6507.94 | W29: =ROUND($O$29,2) -> 6507.94 | X29: 7496.5341 | Y29: 675.30766 | Z29: =X29 -> 7496.5341 | AA29: =Y29 -> 675.30766 | AB29: =Z29 -> 7496.5341 | AC29: =AA29 -> 675.30766 | AD29: =AB29 -> 7496.5341 | AE29: =AC29 -> 675.30766 | AF29: =AD29 -> 7496.5341 | AG29: 675.31 | AH29: 7496.5341 | AI29: 675.31 | AJ29: 7496.53 | AK29: 675.31 | AL29: 7496.53 | AM29: 675.31 | AN29: =SUM(T29:AM29) -> 91406.495 | AP29: =P29+AN29-AO29 -> 97914.435 | AQ29: =M29-AP29 -> 292561.75 | AS29: =IF(AQ29>H29,(AL29+AM29),0) -> 8171.84 | AT29: =IF(AS29+IF(AS29="0","0",AS29)>$AQ29,0,AS29) -> 8171.84 | AU29: =IF(SUM($AS$29:AT29)+IF(AT29="0","0",AT29)>$AQ29,0,AT29) -> 8171.84 | AV29: =IF(SUM($AS$29:AU29)+IF(AU29="0","0",AU29)>$AQ29,0,AU29) -> 8171.84 | AW29: =IF(SUM($AS$29:AV29)+IF(AV29="0","0",AV29)>$AQ29,0,AV29) -> 8171.84 | AX29: =IF(SUM($AS$29:AW29)+IF(AW29="0","0",AW29)>$AQ29,0,AW29) -> 8171.84 | AY29: =IF(SUM($AS$29:AX29)+IF(AX29="0","0",AX29)>$AQ29,0,AX29) -> 8171.84 | AZ29: =IF(SUM($AS$29:AY29)+IF(AY29="0","0",AY29)>$AQ29,0,AY29) -> 8171.84 | BA29: =IF(SUM($AS$29:AZ29)+IF(AZ29="0","0",AZ29)>$AQ29,0,AZ29) -> 8171.84 | BB29: =IF(SUM($AS$29:BA29)+IF(BA29="0","0",BA29)>$AQ29,0,BA29) -> 8171.84 | ... CN29: =IF(SUM($AS$29:CM29)+IF(CM29="0","0",CM29)>$AQ29,0,CM29) -> 0
A30: 25 | B30: BMW I7 | C30: L 22082 | E30: 45260 | G30: 657142.86 | H30: =G30*30% -> 197142.86 | I30: =G30*70% -> 460000 | J30: 657142.86 | M30: =J30+K30-L30 -> 657142.86 | N30: =G30*20% -> 131428.57 | O30: =ROUND(N30/12,2) -> 10952.38 | P30: 10952.38 | Q30: 20044.362 | R30: 396146.12 | S30: 12616.118 | T30: =ROUND($O$30,2) -> 10952.38 | U30: =ROUND($O$30,2) -> 10952.38 | V30: =ROUND($O$30,2) -> 10952.38 | W30: =ROUND($O$30,2) -> 10952.38 | X30: 12616.118 | Y30: 1136.4977 | Z30: =X30 -> 12616.118 | AA30: =Y30 -> 1136.4977 | AB30: =Z30 -> 12616.118 | AC30: =AA30 -> 1136.4977 | AD30: =AB30 -> 12616.118 | AE30: =AC30 -> 1136.4977 | AF30: =AD30 -> 12616.118 | AG30: 1136.5 | AH30: 12616.118 | AI30: 1136.5 | AJ30: 12616.12 | AK30: 1136.5 | AL30: 12616.12 | AM30: 1136.5 | AN30: =SUM(T30:AM30) -> 153830.46 | AP30: =P30+AN30-AO30 -> 164782.84 | AQ30: =M30-AP30 -> 492360.02 | AS30: =IF(AQ30>H30,(AL30+AM30),0) -> 13752.62 | AT30: =IF(AS30+IF(AS30="0","0",AS30)>$AQ30,0,AS30) -> 13752.62 | AU30: =IF(SUM($AS$30:AT30)+IF(AT30="0","0",AT30)>$AQ30,0,AT30) -> 13752.62 | AV30: =IF(SUM($AS$30:AU30)+IF(AU30="0","0",AU30)>$AQ30,0,AU30) -> 13752.62 | AW30: =IF(SUM($AS$30:AV30)+IF(AV30="0","0",AV30)>$AQ30,0,AV30) -> 13752.62 | AX30: =IF(SUM($AS$30:AW30)+IF(AW30="0","0",AW30)>$AQ30,0,AW30) -> 13752.62 | AY30: =IF(SUM($AS$30:AX30)+IF(AX30="0","0",AX30)>$AQ30,0,AX30) -> 13752.62 | AZ30: =IF(SUM($AS$30:AY30)+IF(AY30="0","0",AY30)>$AQ30,0,AY30) -> 13752.62 | BA30: =IF(SUM($AS$30:AZ30)+IF(AZ30="0","0",AZ30)>$AQ30,0,AZ30) -> 13752.62 | BB30: =IF(SUM($AS$30:BA30)+IF(BA30="0","0",BA30)>$AQ30,0,BA30) -> 13752.62 | ... CN30: =IF(SUM($AS$30:CM30)+IF(CM30="0","0",CM30)>$AQ30,0,CM30) -> 0
A31: 26 | B31: BMW I7 | C31: L 25784 | E31: 45268 | G31: 657142.86 | H31: =G31*30% -> 197142.86 | I31: =G31*70% -> 460000 | J31: 657142.86 | M31: =J31+K31-L31 -> 657142.86 | N31: =G31*20% -> 131428.57 | O31: =ROUND(N31/12,2) -> 10952.38 | P31: 7772.66 | Q31: 19863.351 | R31: 399506.85 | S31: 12616.006 | T31: =ROUND($O$31,2) -> 10952.38 | U31: =ROUND($O$31,2) -> 10952.38 | V31: =ROUND($O$31,2) -> 10952.38 | W31: =ROUND($O$31,2) -> 10952.38 | X31: 12616.006 | Y31: 1113.8714 | Z31: =X31 -> 12616.006 | AA31: =Y31 -> 1113.8714 | AB31: =Z31 -> 12616.006 | AC31: =AA31 -> 1113.8714 | AD31: =AB31 -> 12616.006 | AE31: =AC31 -> 1113.8714 | AF31: =AD31 -> 12616.006 | AG31: 1113.87 | AH31: 12616.006 | AI31: 1113.87 | AJ31: 12616.01 | AK31: 1113.87 | AL31: 12616.01 | AM31: 1113.87 | AN31: =SUM(T31:AM31) -> 153648.54 | AP31: =P31+AN31-AO31 -> 161421.2 | AQ31: =M31-AP31 -> 495721.66 | AS31: =IF(AQ31>H31,(AL31+AM31),0) -> 13729.88 | AT31: =IF(AS31+IF(AS31="0","0",AS31)>$AQ31,0,AS31) -> 13729.88 | AU31: =IF(SUM($AS$31:AT31)+IF(AT31="0","0",AT31)>$AQ31,0,AT31) -> 13729.88 | AV31: =IF(SUM($AS$31:AU31)+IF(AU31="0","0",AU31)>$AQ31,0,AU31) -> 13729.88 | AW31: =IF(SUM($AS$31:AV31)+IF(AV31="0","0",AV31)>$AQ31,0,AV31) -> 13729.88 | AX31: =IF(SUM($AS$31:AW31)+IF(AW31="0","0",AW31)>$AQ31,0,AW31) -> 13729.88 | AY31: =IF(SUM($AS$31:AX31)+IF(AX31="0","0",AX31)>$AQ31,0,AX31) -> 13729.88 | AZ31: =IF(SUM($AS$31:AY31)+IF(AY31="0","0",AY31)>$AQ31,0,AY31) -> 13729.88 | BA31: =IF(SUM($AS$31:AZ31)+IF(AZ31="0","0",AZ31)>$AQ31,0,AZ31) -> 13729.88 | BB31: =IF(SUM($AS$31:BA31)+IF(BA31="0","0",BA31)>$AQ31,0,BA31) -> 13729.88 | ... CN31: =IF(SUM($AS$31:CM31)+IF(CM31="0","0",CM31)>$AQ31,0,CM31) -> 0
A32: 27 | B32: Mercedes V-Class Extra long | C32: L 23498 | E32: 45350 | G32: 342857.14 | H32: =G32*30% -> 102857.14 | I32: =G32*70% -> 240000 | K32: 342857.14 | M32: =J32+K32-L32 -> 342857.14 | N32: =G32*20% -> 68571.428 | O32: =ROUND(N32/12,2) -> 5714.29 | P32: 0 | Q32: 7874.751 | R32: 226410.96 | S32: 6581.7139 | T32: 0 | U32: 0 | V32: =ROUND($O$32,2) -> 5714.29 | W32: =ROUND($O$32,2) -> 5714.29 | X32: 6581.7139 | Y32: 270.05762 | Z32: =X32 -> 6581.7139 | AA32: =Y32 -> 270.05762 | AB32: =Z32 -> 6581.7139 | AC32: =AA32 -> 270.05762 | AD32: =AB32 -> 6581.7139 | AE32: =AC32 -> 270.05762 | AF32: =AD32 -> 6581.7139 | AG32: 270.06 | AH32: 6581.7139 | AI32: 270.06 | AJ32: 6581.71 | AK32: 270.06 | AL32: 6581.71 | AM32: 270.06 | AN32: =SUM(T32:AM32) -> 66242.754 | AP32: =P32+AN32-AO32 -> 66242.754 | AQ32: =M32-AP32 -> 276614.39 | AS32: =IF(AQ32>H32,(AL32+AM32),0) -> 6851.77 | AT32: =IF(AS32+IF(AS32="0","0",AS32)>$AQ32,0,AS32) -> 6851.77 | AU32: =IF(SUM($AS$32:AT32)+IF(AT32="0","0",AT32)>$AQ32,0,AT32) -> 6851.77 | AV32: =IF(SUM($AS$32:AU32)+IF(AU32="0","0",AU32)>$AQ32,0,AU32) -> 6851.77 | AW32: =IF(SUM($AS$32:AV32)+IF(AV32="0","0",AV32)>$AQ32,0,AV32) -> 6851.77 | AX32: =IF(SUM($AS$32:AW32)+IF(AW32="0","0",AW32)>$AQ32,0,AW32) -> 6851.77 | AY32: =IF(SUM($AS$32:AX32)+IF(AX32="0","0",AX32)>$AQ32,0,AX32) -> 6851.77 | AZ32: =IF(SUM($AS$32:AY32)+IF(AY32="0","0",AY32)>$AQ32,0,AY32) -> 6851.77 | BA32: =IF(SUM($AS$32:AZ32)+IF(AZ32="0","0",AZ32)>$AQ32,0,AZ32) -> 6851.77 | BB32: =IF(SUM($AS$32:BA32)+IF(BA32="0","0",BA32)>$AQ32,0,BA32) -> 6851.77 | ... CN32: =IF(SUM($AS$32:CM32)+IF(CM32="0","0",CM32)>$AQ32,0,CM32) -> 0
A33: 28 | B33: Mercedes V-Class Extra long | C33: L 25673 | E33: 45350 | G33: 342857.14 | H33: =G33*30% -> 102857.14 | I33: =G33*70% -> 240000 | K33: 342857.14 | M33: =J33+K33-L33 -> 342857.14 | N33: =G33*20% -> 68571.428 | O33: =ROUND(N33/12,2) -> 5714.29 | P33: 0 | Q33: 7874.751 | R33: 226410.96 | S33: 6581.7139 | T33: 0 | U33: 0 | V33: =ROUND($O$33,2) -> 5714.29 | W33: =ROUND($O$33,2) -> 5714.29 | X33: 6581.7139 | Y33: 270.05762 | Z33: =X33 -> 6581.7139 | AA33: =Y33 -> 270.05762 | AB33: =Z33 -> 6581.7139 | AC33: =AA33 -> 270.05762 | AD33: =AB33 -> 6581.7139 | AE33: =AC33 -> 270.05762 | AF33: =AD33 -> 6581.7139 | AG33: 270.06 | AH33: 6581.7139 | AI33: 270.06 | AJ33: 6581.71 | AK33: 270.06 | AL33: 6581.71 | AM33: 270.06 | AN33: =SUM(T33:AM33) -> 66242.754 | AP33: =P33+AN33-AO33 -> 66242.754 | AQ33: =M33-AP33 -> 276614.39 | AS33: =IF(AQ33>H33,(AL33+AM33),0) -> 6851.77 | AT33: =IF(AS33+IF(AS33="0","0",AS33)>$AQ33,0,AS33) -> 6851.77 | AU33: =IF(SUM($AS$33:AT33)+IF(AT33="0","0",AT33)>$AQ33,0,AT33) -> 6851.77 | AV33: =IF(SUM($AS$33:AU33)+IF(AU33="0","0",AU33)>$AQ33,0,AU33) -> 6851.77 | AW33: =IF(SUM($AS$33:AV33)+IF(AV33="0","0",AV33)>$AQ33,0,AV33) -> 6851.77 | AX33: =IF(SUM($AS$33:AW33)+IF(AW33="0","0",AW33)>$AQ33,0,AW33) -> 6851.77 | AY33: =IF(SUM($AS$33:AX33)+IF(AX33="0","0",AX33)>$AQ33,0,AX33) -> 6851.77 | AZ33: =IF(SUM($AS$33:AY33)+IF(AY33="0","0",AY33)>$AQ33,0,AY33) -> 6851.77 | BA33: =IF(SUM($AS$33:AZ33)+IF(AZ33="0","0",AZ33)>$AQ33,0,AZ33) -> 6851.77 | BB33: =IF(SUM($AS$33:BA33)+IF(BA33="0","0",BA33)>$AQ33,0,BA33) -> 6851.77 | ... CN33: =IF(SUM($AS$33:CM33)+IF(CM33="0","0",CM33)>$AQ33,0,CM33) -> 0
A34: 29 | B34: BMW G70 735i | C34: L 26082 | E34: 45356 | G34: 448571.43 | H34: =G34*30% -> 134571.43 | I34: =G34*70% -> 314000 | K34: 448571 | M34: =J34+K34-L34 -> 448571 | N34: =G34*20% -> 89714.286 | O34: =ROUND(N34/12,2) -> 7476.19 | P34: 0 | Q34: 10029.258 | R34: 297941.55 | S34: 8611.0276 | T34: 0 | V34: =ROUND($O$34*25/31,2) -> 6029.19 | W34: =ROUND($O$34,2) -> 7476.19 | X34: 8611.0276 | Y34: 319.13344 | Z34: =X34 -> 8611.0276 | AA34: =Y34 -> 319.13344 | AB34: =Z34 -> 8611.0276 | AC34: =AA34 -> 319.13344 | AD34: =AB34 -> 8611.0276 | AE34: =AC34 -> 319.13344 | AF34: =AD34 -> 8611.0276 | AG34: 319.13 | AH34: 8611.0276 | AI34: 319.13 | AJ34: 8611.03 | AK34: 319.13 | AL34: 8611.03 | AM34: 319.13 | AN34: =SUM(T34:AM34) -> 84946.659 | AP34: =P34+AN34-AO34 -> 84946.659 | AQ34: =M34-AP34 -> 363624.34 | AS34: =IF(AQ34>H34,(AL34+AM34),0) -> 8930.16 | AT34: =IF(AS34+IF(AS34="0","0",AS34)>$AQ34,0,AS34) -> 8930.16 | AU34: =IF(SUM($AS$34:AT34)+IF(AT34="0","0",AT34)>$AQ34,0,AT34) -> 8930.16 | AV34: =IF(SUM($AS$34:AU34)+IF(AU34="0","0",AU34)>$AQ34,0,AU34) -> 8930.16 | AW34: =IF(SUM($AS$34:AV34)+IF(AV34="0","0",AV34)>$AQ34,0,AV34) -> 8930.16 | AX34: =IF(SUM($AS$34:AW34)+IF(AW34="0","0",AW34)>$AQ34,0,AW34) -> 8930.16 | AY34: =IF(SUM($AS$34:AX34)+IF(AX34="0","0",AX34)>$AQ34,0,AX34) -> 8930.16 | AZ34: =IF(SUM($AS$34:AY34)+IF(AY34="0","0",AY34)>$AQ34,0,AY34) -> 8930.16 | BA34: =IF(SUM($AS$34:AZ34)+IF(AZ34="0","0",AZ34)>$AQ34,0,AZ34) -> 8930.16 | BB34: =IF(SUM($AS$34:BA34)+IF(BA34="0","0",BA34)>$AQ34,0,BA34) -> 8930.16 | ... CN34: =IF(SUM($AS$34:CM34)+IF(CM34="0","0",CM34)>$AQ34,0,CM34) -> 0
A35: 30 | B35: BMW G70 735i | C35: L 26081 | E35: 45356 | G35: 448571.43 | H35: =G35*30% -> 134571.43 | I35: =G35*70% -> 314000 | K35: 448571 | M35: =J35+K35-L35 -> 448571 | N35: =G35*20% -> 89714.286 | O35: =ROUND(N35/12,2) -> 7476.19 | P35: 0 | Q35: 10029.258 | R35: 297941.55 | S35: 8611.0276 | T35: 0 | V35: =ROUND($O$35*25/31,2) -> 6029.19 | W35: =ROUND($O$35,2) -> 7476.19 | X35: 8611.0276 | Y35: 319.13344 | Z35: =X35 -> 8611.0276 | AA35: =Y35 -> 319.13344 | AB35: =Z35 -> 8611.0276 | AC35: =AA35 -> 319.13344 | AD35: =AB35 -> 8611.0276 | AE35: =AC35 -> 319.13344 | AF35: =AD35 -> 8611.0276 | AG35: 319.13 | AH35: 8611.0276 | AI35: 319.13 | AJ35: 8611.03 | AK35: 319.13 | AL35: 8611.03 | AM35: 319.13 | AN35: =SUM(T35:AM35) -> 84946.659 | AP35: =P35+AN35-AO35 -> 84946.659 | AQ35: =M35-AP35 -> 363624.34 | AS35: =IF(AQ35>H35,(AL35+AM35),0) -> 8930.16 | AT35: =IF(AS35+IF(AS35="0","0",AS35)>$AQ35,0,AS35) -> 8930.16 | AU35: =IF(SUM($AS$35:AT35)+IF(AT35="0","0",AT35)>$AQ35,0,AT35) -> 8930.16 | AV35: =IF(SUM($AS$35:AU35)+IF(AU35="0","0",AU35)>$AQ35,0,AU35) -> 8930.16 | AW35: =IF(SUM($AS$35:AV35)+IF(AV35="0","0",AV35)>$AQ35,0,AV35) -> 8930.16 | AX35: =IF(SUM($AS$35:AW35)+IF(AW35="0","0",AW35)>$AQ35,0,AW35) -> 8930.16 | AY35: =IF(SUM($AS$35:AX35)+IF(AX35="0","0",AX35)>$AQ35,0,AX35) -> 8930.16 | AZ35: =IF(SUM($AS$35:AY35)+IF(AY35="0","0",AY35)>$AQ35,0,AY35) -> 8930.16 | BA35: =IF(SUM($AS$35:AZ35)+IF(AZ35="0","0",AZ35)>$AQ35,0,AZ35) -> 8930.16 | BB35: =IF(SUM($AS$35:BA35)+IF(BA35="0","0",BA35)>$AQ35,0,BA35) -> 8930.16 | ... CN35: =IF(SUM($AS$35:CM35)+IF(CM35="0","0",CM35)>$AQ35,0,CM35) -> 0
A36: 31 | B36: BMW G60 520. | C36: L 22197 | E36: 45412 | G36: 247619.05 | H36: =G36*30% -> 74285.715 | I36: =G36*70% -> 173333.33 | K36: 247619.05 | M36: =J36+K36-L36 -> 247619.05 | N36: =G36*20% -> 49523.81 | O36: =ROUND(N36/12,2) -> 4126.98 | P36: 0 | Q36: 0 | R36: 173333.33 | S36: 4753.1993 | T36: 0 | U36: 0 | V36: 0 | W36: 0 | X36: 0 | Y36: 0 | Z36: =S36 -> 4753.1993 | AA36: 0 | AB36: =S36 -> 4753.1993 | AC36: 0 | AD36: =S36 -> 4753.1993 | AE36: 0 | AF36: 4753.2 | AG36: 0 | AH36: 4753.2 | AI36: 0 | AJ36: 4753.2 | AK36: 0 | AL36: 4753.2 | AM36: 0 | AN36: =SUM(T36:AM36) -> 33272.398 | AP36: =P36+AN36-AO36 -> 33272.398 | AQ36: =M36-AP36 -> 214346.65 | AS36: =IF(AQ36>H36,(AL36+AM36),0) -> 4753.2 | AT36: =IF(AS36+IF(AS36="0","0",AS36)>$AQ36,0,AS36) -> 4753.2 | AU36: =IF(SUM($AS$36:AT36)+IF(AT36="0","0",AT36)>$AQ36,0,AT36) -> 4753.2 | AV36: =IF(SUM($AS$36:AU36)+IF(AU36="0","0",AU36)>$AQ36,0,AU36) -> 4753.2 | AW36: =IF(SUM($AS$36:AV36)+IF(AV36="0","0",AV36)>$AQ36,0,AV36) -> 4753.2 | AX36: =IF(SUM($AS$36:AW36)+IF(AW36="0","0",AW36)>$AQ36,0,AW36) -> 4753.2 | AY36: =IF(SUM($AS$36:AX36)+IF(AX36="0","0",AX36)>$AQ36,0,AX36) -> 4753.2 | AZ36: =IF(SUM($AS$36:AY36)+IF(AY36="0","0",AY36)>$AQ36,0,AY36) -> 4753.2 | BA36: =IF(SUM($AS$36:AZ36)+IF(AZ36="0","0",AZ36)>$AQ36,0,AZ36) -> 4753.2 | BB36: =IF(SUM($AS$36:BA36)+IF(BA36="0","0",BA36)>$AQ36,0,BA36) -> 4753.2 | ... CN36: =IF(SUM($AS$36:CM36)+IF(CM36="0","0",CM36)>$AQ36,0,CM36) -> 0
B37: Mercedes S Class | E37: 45687 | G37: ='Dep-Vehicle monthly Dec 2026'!F25 -> 623809.52 | H37: =G37*30% -> 187142.86 | I37: =G37*70% -> 436666.66 | AL37: =I37/36 -> 12129.63 | AQ37: =I37 -> 436666.66 | AT37: =IF(AQ37>H37,(AL37+AM37),0) -> 12129.63 | AU37: =IF(AT37+IF(AT37="0","0",AT37)>$AQ37,0,AT37) -> 12129.63 | AV37: =IF(SUM($AT$37:AU37)+IF(AU37="0","0",AU37)>$AQ37,0,AU37) -> 12129.63 | AW37: =IF(SUM($AT$37:AV37)+IF(AV37="0","0",AV37)>$AQ37,0,AV37) -> 12129.63 | AX37: =IF(SUM($AT$37:AW37)+IF(AW37="0","0",AW37)>$AQ37,0,AW37) -> 12129.63 | AY37: =IF(SUM($AT$37:AX37)+IF(AX37="0","0",AX37)>$AQ37,0,AX37) -> 12129.63 | AZ37: =IF(SUM($AT$37:AY37)+IF(AY37="0","0",AY37)>$AQ37,0,AY37) -> 12129.63 | BA37: =IF(SUM($AT$37:AZ37)+IF(AZ37="0","0",AZ37)>$AQ37,0,AZ37) -> 12129.63 | BB37: =IF(SUM($AT$37:BA37)+IF(BA37="0","0",BA37)>$AQ37,0,BA37) -> 12129.63 | BC37: =IF(SUM($AT$37:BB37)+IF(BB37="0","0",BB37)>$AQ37,0,BB37) -> 12129.63 | ... CO37: =IF(SUM($AT$37:CN37)+IF(CN37="0","0",CN37)>$AQ37,0,CN37) -> 0
B38: Mercedes S Class | E38: 45687 | G38: ='Dep-Vehicle monthly Dec 2026'!F26 -> 623809.52 | H38: =G38*30% -> 187142.86 | I38: =G38*70% -> 436666.66 | AL38: =I38/36 -> 12129.63 | AQ38: =I38 -> 436666.66 | AT38: =IF(AQ38>H38,(AL38+AM38),0) -> 12129.63 | AU38: =IF(AT38+IF(AT38="0","0",AT38)>$AQ38,0,AT38) -> 12129.63 | AV38: =IF(SUM($AT$38:AU38)+IF(AU38="0","0",AU38)>$AQ38,0,AU38) -> 12129.63 | AW38: =IF(SUM($AT$38:AV38)+IF(AV38="0","0",AV38)>$AQ38,0,AV38) -> 12129.63 | AX38: =IF(SUM($AT$38:AW38)+IF(AW38="0","0",AW38)>$AQ38,0,AW38) -> 12129.63 | AY38: =IF(SUM($AT$38:AX38)+IF(AX38="0","0",AX38)>$AQ38,0,AX38) -> 12129.63 | AZ38: =IF(SUM($AT$38:AY38)+IF(AY38="0","0",AY38)>$AQ38,0,AY38) -> 12129.63 | BA38: =IF(SUM($AT$38:AZ38)+IF(AZ38="0","0",AZ38)>$AQ38,0,AZ38) -> 12129.63 | BB38: =IF(SUM($AT$38:BA38)+IF(BA38="0","0",BA38)>$AQ38,0,BA38) -> 12129.63 | BC38: =IF(SUM($AT$38:BB38)+IF(BB38="0","0",BB38)>$AQ38,0,BB38) -> 12129.63 | ... CO38: =IF(SUM($AT$38:CN38)+IF(CN38="0","0",CN38)>$AQ38,0,CN38) -> 0
B39: Mercedes S Class | E39: 45687 | G39: ='Dep-Vehicle monthly Dec 2026'!F27 -> 623809.52 | H39: =G39*30% -> 187142.86 | I39: =G39*70% -> 436666.66 | AL39: =I39/36 -> 12129.63 | AQ39: =I39 -> 436666.66 | AT39: =IF(AQ39>H39,(AL39+AM39),0) -> 12129.63 | AU39: =IF(AT39+IF(AT39="0","0",AT39)>$AQ39,0,AT39) -> 12129.63 | AV39: =IF(SUM($AT$39:AU39)+IF(AU39="0","0",AU39)>$AQ39,0,AU39) -> 12129.63 | AW39: =IF(SUM($AT$39:AV39)+IF(AV39="0","0",AV39)>$AQ39,0,AV39) -> 12129.63 | AX39: =IF(SUM($AT$39:AW39)+IF(AW39="0","0",AW39)>$AQ39,0,AW39) -> 12129.63 | AY39: =IF(SUM($AT$39:AX39)+IF(AX39="0","0",AX39)>$AQ39,0,AX39) -> 12129.63 | AZ39: =IF(SUM($AT$39:AY39)+IF(AY39="0","0",AY39)>$AQ39,0,AY39) -> 12129.63 | BA39: =IF(SUM($AT$39:AZ39)+IF(AZ39="0","0",AZ39)>$AQ39,0,AZ39) -> 12129.63 | BB39: =IF(SUM($AT$39:BA39)+IF(BA39="0","0",BA39)>$AQ39,0,BA39) -> 12129.63 | BC39: =IF(SUM($AT$39:BB39)+IF(BB39="0","0",BB39)>$AQ39,0,BB39) -> 12129.63 | ... CO39: =IF(SUM($AT$39:CN39)+IF(CN39="0","0",CN39)>$AQ39,0,CN39) -> 0
B40: BMW Série 7 | E40: 45716 | G40: ='Dep-Vehicle monthly Dec 2026'!F31 -> 485714.29 | H40: =G40*30% -> 145714.29 | I40: =G40*70% -> 340000 | AL40: =I40/36 -> 9444.4445 | AQ40: =I40 -> 340000 | AU40: =IF(AQ40>H40,(AL40+AM40),0) -> 9444.4445 | AV40: =IF(AU40+IF(AU40="0","0",AU40)>$AQ40,0,AU40) -> 9444.4445 | AW40: =IF(SUM($AU$40:AV40)+IF(AV40="0","0",AV40)>$AQ40,0,AV40) -> 9444.4445 | AX40: =IF(SUM($AU$40:AW40)+IF(AW40="0","0",AW40)>$AQ40,0,AW40) -> 9444.4445 | AY40: =IF(SUM($AU$40:AX40)+IF(AX40="0","0",AX40)>$AQ40,0,AX40) -> 9444.4445 | AZ40: =IF(SUM($AU$40:AY40)+IF(AY40="0","0",AY40)>$AQ40,0,AY40) -> 9444.4445 | BA40: =IF(SUM($AU$40:AZ40)+IF(AZ40="0","0",AZ40)>$AQ40,0,AZ40) -> 9444.4445 | BB40: =IF(SUM($AU$40:BA40)+IF(BA40="0","0",BA40)>$AQ40,0,BA40) -> 9444.4445 | BC40: =IF(SUM($AU$40:BB40)+IF(BB40="0","0",BB40)>$AQ40,0,BB40) -> 9444.4445 | BD40: =IF(SUM($AU$40:BC40)+IF(BC40="0","0",BC40)>$AQ40,0,BC40) -> 9444.4445 | ... CP40: =IF(SUM($AU$40:CO40)+IF(CO40="0","0",CO40)>$AQ40,0,CO40) -> 0
B41: Mercedees V Class | E41: 45716 | G41: ='Dep-Vehicle monthly Dec 2026'!F28 -> 480124.47 | H41: =G41*30% -> 144037.34 | I41: =G41*70% -> 336087.13 | AL41: =I41/36 -> 9335.7536 | AQ41: =I41 -> 336087.13 | AU41: =IF(AQ41>H41,(AL41+AM41),0) -> 9335.7536 | AV41: =IF(AU41+IF(AU41="0","0",AU41)>$AQ41,0,AU41) -> 9335.7536 | AW41: =IF(SUM($AU$41:AV41)+IF(AV41="0","0",AV41)>$AQ41,0,AV41) -> 9335.7536 | AX41: =IF(SUM($AU$41:AW41)+IF(AW41="0","0",AW41)>$AQ41,0,AW41) -> 9335.7536 | AY41: =IF(SUM($AU$41:AX41)+IF(AX41="0","0",AX41)>$AQ41,0,AX41) -> 9335.7536 | AZ41: =IF(SUM($AU$41:AY41)+IF(AY41="0","0",AY41)>$AQ41,0,AY41) -> 9335.7536 | BA41: =IF(SUM($AU$41:AZ41)+IF(AZ41="0","0",AZ41)>$AQ41,0,AZ41) -> 9335.7536 | BB41: =IF(SUM($AU$41:BA41)+IF(BA41="0","0",BA41)>$AQ41,0,BA41) -> 9335.7536 | BC41: =IF(SUM($AU$41:BB41)+IF(BB41="0","0",BB41)>$AQ41,0,BB41) -> 9335.7536 | BD41: =IF(SUM($AU$41:BC41)+IF(BC41="0","0",BC41)>$AQ41,0,BC41) -> 9335.7536 | ... CP41: =IF(SUM($AU$41:CO41)+IF(CO41="0","0",CO41)>$AQ41,0,CO41) -> 0
B42: Mercedes S Class | E42: 45747 | G42: ='Dep-Vehicle monthly Dec 2026'!F29 -> 576341.81 | H42: =G42*30% -> 172902.54 | I42: =G42*70% -> 403439.27 | AL42: =I42/36 -> 11206.646 | AQ42: =I42 -> 403439.27 | AV42: =IF(AQ42>H42,(AL42+AM42),0) -> 11206.646 | AW42: =IF(AV42+IF(AV42="0","0",AV42)>$AQ42,0,AV42) -> 11206.646 | AX42: =IF(SUM($AV$42:AW42)+IF(AW42="0","0",AW42)>$AQ42,0,AW42) -> 11206.646 | AY42: =IF(SUM($AV$42:AX42)+IF(AX42="0","0",AX42)>$AQ42,0,AX42) -> 11206.646 | AZ42: =IF(SUM($AV$42:AY42)+IF(AY42="0","0",AY42)>$AQ42,0,AY42) -> 11206.646 | BA42: =IF(SUM($AV$42:AZ42)+IF(AZ42="0","0",AZ42)>$AQ42,0,AZ42) -> 11206.646 | BB42: =IF(SUM($AV$42:BA42)+IF(BA42="0","0",BA42)>$AQ42,0,BA42) -> 11206.646 | BC42: =IF(SUM($AV$42:BB42)+IF(BB42="0","0",BB42)>$AQ42,0,BB42) -> 11206.646 | BD42: =IF(SUM($AV$42:BC42)+IF(BC42="0","0",BC42)>$AQ42,0,BC42) -> 11206.646 | BE42: =IF(SUM($AV$42:BD42)+IF(BD42="0","0",BD42)>$AQ42,0,BD42) -> 11206.646 | ... CQ42: =IF(SUM($AV$42:CP42)+IF(CP42="0","0",CP42)>$AQ42,0,CP42) -> 0
B43: Cadillac Escalade | E43: 45412 | G43: ='Dep-Vehicle monthly Dec 2026'!F32 -> 504761.9 | H43: =G43*30% -> 151428.57 | I43: =G43*70% -> 353333.33 | AL43: =I43/36 -> 9814.8147 | AQ43: =I43 -> 353333.33 | AW43: =IF(AQ43>H43,(AL43+AM43),0) -> 9814.8147 | AX43: =IF(AW43+IF(AW43="0","0",AW43)>$AQ43,0,AW43) -> 9814.8147 | AY43: =IF(SUM($AW$43:AX43)+IF(AX43="0","0",AX43)>$AQ43,0,AX43) -> 9814.8147 | AZ43: =IF(SUM($AW$43:AY43)+IF(AY43="0","0",AY43)>$AQ43,0,AY43) -> 9814.8147 | BA43: =IF(SUM($AW$43:AZ43)+IF(AZ43="0","0",AZ43)>$AQ43,0,AZ43) -> 9814.8147 | BB43: =IF(SUM($AW$43:BA43)+IF(BA43="0","0",BA43)>$AQ43,0,BA43) -> 9814.8147 | BC43: =IF(SUM($AW$43:BB43)+IF(BB43="0","0",BB43)>$AQ43,0,BB43) -> 9814.8147 | BD43: =IF(SUM($AW$43:BC43)+IF(BC43="0","0",BC43)>$AQ43,0,BC43) -> 9814.8147 | BE43: =IF(SUM($AW$43:BD43)+IF(BD43="0","0",BD43)>$AQ43,0,BD43) -> 9814.8147 | BF43: =IF(SUM($AW$43:BE43)+IF(BE43="0","0",BE43)>$AQ43,0,BE43) -> 9814.8147 | ... CR43: =IF(SUM($AW$43:CQ43)+IF(CQ43="0","0",CQ43)>$AQ43,0,CQ43) -> 0
AP44: =P44+AN44-AO44 -> 0 | AQ44: =M44-AP44 -> 0
B50: Sold Vehicles | AQ50: =M50-AP50 -> 0
AP69: =P69+AN69-AO69 -> 0
J70: =SUM(J6:J69) -> 12661314 | K70: =SUM(K6:K69) -> 1830475.3 | L70: =SUM(L6:L69) -> 0 | M70: =SUM(M3:M69) -> 14491789 | N70: =SUM(N6:N69) -> 2857063.8 | O70: =SUM(O6:O69) -> 238088.67 | P70: =SUM(P6:P69) -> 2067191.1 | T70: =SUM(T6:T69) -> 207580.73 | U70: =SUM(U6:U69) -> 207580.73 | V70: =SUM(V6:V69) -> 231067.69 | W70: =SUM(W6:W69) -> 233961.69 | X70: =SUM(X6:X69) -> 269743.01 | Y70: =SUM(Y6:Y69) -> 65779.94 | Z70: =SUM(Z6:Z69) -> 274496.21 | AA70: =SUM(AA6:AA69) -> 65779.94 | ... AO70: =SUM(AO6:AO69) -> 0 | AP70: =SUM(AP3:AP69) -> 5561165.9 | AQ70: =SUM(AQ3:AQ69) -> 11673483
AS71: =SUM(AS6:AS70) -> 272996.81 | AT71: =SUM(AT6:AT70) -> 309385.7 | AU71: =SUM(AU6:AU70) -> 328165.9 | AV71: =SUM(AV6:AV70) -> 339372.54 | AW71: =SUM(AW6:AW70) -> 349187.36 | AX71: =SUM(AX6:AX70) -> 349187.36 | AY71: =SUM(AY6:AY70) -> 349187.36 | AZ71: =SUM(AZ6:AZ70) -> 349187.36 | ... CN71: =SUM(CN6:CN70) -> 0
AH72: Zoho | AJ72: Zoho | AL72: Zoho | AS72: =AS71/-4/1000 -> -68.249202 | AT72: =AT71/-4/1000 -> -77.346425 | AU72: =AU71/-4/1000 -> -82.041474 | AV72: =AV71/-4/1000 -> -84.843136 | AW72: =AW71/-4/1000 -> -87.296839 | AX72: =AX71/-4/1000 -> -87.296839 | AY72: =AY71/-4/1000 -> -87.296839 | AZ72: =AZ71/-4/1000 -> -87.296839 | ... CN72: =CN71/-4/1000 -> 0
AH74: Diff | AI74: =+AI70-AI72-AI73 -> 62222.43 | AJ74: Diff | AL74: Diff
M75: 14491790
M76: =+M70-M75 -> -1.24
AN77: Balance as per Zoho on 31.12.2024 | AP77: 5561164.9 | AQ77: =14491790.4-5561164.91 -> 8930625.5
AP78: =+AP70-AP77 -> 1.0048739 | AQ78: =+AQ70-AQ77 -> 2742857.5
